[{"game_id": "0022201206", "game_date": "Apr 07, 2023", "matchup": "BOS vs. TOR", "wl": "W", "min": 20.0, "fgm": 7, "fga": 12, "fg_pct": 0.583, "fg3m": 0, "fg3a": 5, "fg3_pct": 0.0, "ftm": 7, "fta": 9, "ft_pct": 0.778, "oreb": 1, "dreb": 2, "reb": 3, "ast": 4, "stl": 0, "blk": 0, "tov": 3, "pf": 2, "pts": 21, "plus_minus": 23}, {"game_id": "0022201181", "game_date": "Apr 04, 2023", "matchup": "BOS @ PHI", "wl": "L", "min": 38.0, "fgm": 7, "fga": 20, "fg_pct": 0.35, "fg3m": 2, "fg3a": 8, "fg3_pct": 0.25, "ftm": 3, "fta": 5, "ft_pct": 0.6, "oreb": 1, "dreb": 5, "reb": 6, "ast": 6, "stl": 3, "blk": 0, "tov": 2, "pf": 2, "pts": 19, "plus_minus": -13}, {"game_id": "0022201152", "game_date": "Mar 31, 2023", "matchup": "BOS vs. UTA", "wl": "W", "min": 36.0, "fgm": 12, "fga": 17, "fg_pct": 0.706, "fg3m": 5, "fg3a": 8, "fg3_pct": 0.625, "ftm": 10, "fta": 11, "ft_pct": 0.909, "oreb": 1, "dreb": 10, "reb": 11, "ast": 3, "stl": 3, "blk": 0, "tov": 0, "pf": 4, "pts": 39, "plus_minus": 7}, {"game_id": "0022201146", "game_date": "Mar 30, 2023", "matchup": "BOS @ MIL", "wl": "W", "min": 31.0, "fgm": 12, "fga": 18, "fg_pct": 0.667, "fg3m": 8, "fg3a": 10, "fg3_pct": 0.8, "ftm": 8, "fta": 8, "ft_pct": 1.0, "oreb": 1, "dreb": 7, "reb": 8, "ast": 1, "stl": 0, "blk": 0, "tov": 0, "pf": 1, "pts": 40, "plus_minus": 36}, {"game_id": "0022201130", "game_date": "Mar 28, 2023", "matchup": "BOS @ WAS", "wl": "L", "min": 32.0, "fgm": 11, "fga": 19, "fg_pct": 0.579, "fg3m": 2, "fg3a": 7, "fg3_pct": 0.286, "ftm": 4, "fta": 4, "ft_pct": 1.0, "oreb": 0, "dreb": 9, "reb": 9, "ast": 5, "stl": 0, "blk": 1, "tov": 3, "pf": 4, "pts": 28, "plus_minus": -10}, {"game_id": "0022201097", "game_date": "Mar 24, 2023", "matchup": "BOS vs. IND", "wl": "W", "min": 32.0, "fgm": 13, "fga": 24, "fg_pct": 0.542, "fg3m": 3, "fg3a": 9, "fg3_pct": 0.333, "ftm": 5, "fta": 6, "ft_pct": 0.833, "oreb": 0, "dreb": 7, "reb": 7, "ast": 2, "stl": 2, "blk": 0, "tov": 6, "pf": 3, "pts": 34, "plus_minus": 23}, {"game_id": "0022201081", "game_date": "Mar 21, 2023", "matchup": "BOS @ SAC", "wl": "W", "min": 35.0, "fgm": 14, "fga": 25, "fg_pct": 0.56, "fg3m": 2, "fg3a": 7, "fg3_pct": 0.286, "ftm": 6, "fta": 11, "ft_pct": 0.545, "oreb": 1, "dreb": 7, "reb": 8, "ast": 4, "stl": 2, "blk": 0, "tov": 1, "pf": 0, "pts": 36, "plus_minus": 21}, {"game_id": "0022201062", "game_date": "Mar 18, 2023", "matchup": "BOS @ UTA", "wl": "L", "min": 39.0, "fgm": 4, "fga": 12, "fg_pct": 0.333, "fg3m": 3, "fg3a": 8, "fg3_pct": 0.375, "ftm": 4, "fta": 6, "ft_pct": 0.667, "oreb": 0, "dreb": 3, "reb": 3, "ast": 6, "stl": 0, "blk": 1, "tov": 2, "pf": 3, "pts": 15, "plus_minus": -13}, {"game_id": "0022201053", "game_date": "Mar 17, 2023", "matchup": "BOS @ POR", "wl": "W", "min": 36.0, "fgm": 8, "fga": 20, "fg_pct": 0.4, "fg3m": 2, "fg3a": 11, "fg3_pct": 0.182, "ftm": 16, "fta": 18, "ft_pct": 0.889, "oreb": 1, "dreb": 11, "reb": 12, "ast": 4, "stl": 3, "blk": 0, "tov": 5, "pf": 2, "pts": 34, "plus_minus": 11}, {"game_id": "0022201039", "game_date": "Mar 15, 2023", "matchup": "BOS @ MIN", "wl": "W", "min": 37.0, "fgm": 4, "fga": 16, "fg_pct": 0.25, "fg3m": 0, "fg3a": 8, "fg3_pct": 0.0, "ftm": 14, "fta": 16, "ft_pct": 0.875, "oreb": 1, "dreb": 11, "reb": 12, "ast": 2, "stl": 2, "blk": 1, "tov": 2, "pf": 5, "pts": 22, "plus_minus": -3}, {"game_id": "0022201024", "game_date": "Mar 13, 2023", "matchup": "BOS @ HOU", "wl": "L", "min": 41.0, "fgm": 8, "fga": 22, "fg_pct": 0.364, "fg3m": 2, "fg3a": 10, "fg3_pct": 0.2, "ftm": 4, "fta": 4, "ft_pct": 1.0, "oreb": 0, "dreb": 8, "reb": 8, "ast": 6, "stl": 1, "blk": 0, "tov": 4, "pf": 1, "pts": 22, "plus_minus": -2}, {"game_id": "0022201008", "game_date": "Mar 11, 2023", "matchup": "BOS @ ATL", "wl": "W", "min": 35.0, "fgm": 12, "fga": 25, "fg_pct": 0.48, "fg3m": 5, "fg3a": 14, "fg3_pct": 0.357, "ftm": 5, "fta": 6, "ft_pct": 0.833, "oreb": 0, "dreb": 15, "reb": 15, "ast": 6, "stl": 0, "blk": 1, "tov": 1, "pf": 5, "pts": 34, "plus_minus": 13}, {"game_id": "0022200986", "game_date": "Mar 08, 2023", "matchup": "BOS vs. POR", "wl": "W", "min": 31.0, "fgm": 11, "fga": 17, "fg_pct": 0.647, "fg3m": 6, "fg3a": 10, "fg3_pct": 0.6, "ftm": 2, "fta": 4, "ft_pct": 0.5, "oreb": 1, "dreb": 6, "reb": 7, "ast": 2, "stl": 1, "blk": 0, "tov": 3, "pf": 0, "pts": 30, "plus_minus": 21}, {"game_id": "0022200969", "game_date": "Mar 05, 2023", "matchup": "BOS vs. NYK", "wl": "L", "min": 49.0, "fgm": 12, "fga": 30, "fg_pct": 0.4, "fg3m": 6, "fg3a": 17, "fg3_pct": 0.353, "ftm": 10, "fta": 12, "ft_pct": 0.833, "oreb": 2, "dreb": 9, "reb": 11, "ast": 6, "stl": 0, "blk": 0, "tov": 2, "pf": 2, "pts": 40, "plus_minus": 4}, {"game_id": "0022200948", "game_date": "Mar 03, 2023", "matchup": "BOS vs. BKN", "wl": "L", "min": 38.0, "fgm": 10, "fga": 23, "fg_pct": 0.435, "fg3m": 0, "fg3a": 7, "fg3_pct": 0.0, "ftm": 2, "fta": 2, "ft_pct": 1.0, "oreb": 1, "dreb": 12, "reb": 13, "ast": 5, "stl": 1, "blk": 2, "tov": 4, "pf": 2, "pts": 22, "plus_minus": -19}, {"game_id": "0022200935", "game_date": "Mar 01, 2023", "matchup": "BOS vs. CLE", "wl": "W", "min": 36.0, "fgm": 13, "fga": 21, "fg_pct": 0.619, "fg3m": 4, "fg3a": 6, "fg3_pct": 0.667, "ftm": 11, "fta": 14, "ft_pct": 0.786, "oreb": 2, "dreb": 9, "reb": 11, "ast": 8, "stl": 0, "blk": 0, "tov": 3, "pf": 1, "pts": 41, "plus_minus": 4}, {"game_id": "0022200921", "game_date": "Feb 27, 2023", "matchup": "BOS @ NYK", "wl": "L", "min": 37.0, "fgm": 6, "fga": 18, "fg_pct": 0.333, "fg3m": 1, "fg3a": 9, "fg3_pct": 0.111, "ftm": 1, "fta": 1, "ft_pct": 1.0, "oreb": 2, "dreb": 5, "reb": 7, "ast": 9, "stl": 1, "blk": 0, "tov": 4, "pf": 1, "pts": 14, "plus_minus": -18}, {"game_id": "0022200908", "game_date": "Feb 25, 2023", "matchup": "BOS @ PHI", "wl": "W", "min": 36.0, "fgm": 7, "fga": 17, "fg_pct": 0.412, "fg3m": 3, "fg3a": 8, "fg3_pct": 0.375, "ftm": 1, "fta": 2, "ft_pct": 0.5, "oreb": 3, "dreb": 10, "reb": 13, "ast": 6, "stl": 0, "blk": 1, "tov": 5, "pf": 1, "pts": 18, "plus_minus": -6}, {"game_id": "0022200887", "game_date": "Feb 23, 2023", "matchup": "BOS @ IND", "wl": "W", "min": 42.0, "fgm": 9, "fga": 25, "fg_pct": 0.36, "fg3m": 3, "fg3a": 12, "fg3_pct": 0.25, "ftm": 10, "fta": 11, "ft_pct": 0.909, "oreb": 3, "dreb": 9, "reb": 12, "ast": 7, "stl": 2, "blk": 1, "tov": 4, "pf": 1, "pts": 31, "plus_minus": -8}, {"game_id": "0022200877", "game_date": "Feb 15, 2023", "matchup": "BOS vs. DET", "wl": "W", "min": 34.0, "fgm": 15, "fga": 24, "fg_pct": 0.625, "fg3m": 6, "fg3a": 10, "fg3_pct": 0.6, "ftm": 2, "fta": 2, "ft_pct": 1.0, "oreb": 0, "dreb": 9, "reb": 9, "ast": 7, "stl": 0, "blk": 0, "tov": 4, "pf": 3, "pts": 38, "plus_minus": 1}, {"game_id": "0022200855", "game_date": "Feb 12, 2023", "matchup": "BOS vs. MEM", "wl": "W", "min": 38.0, "fgm": 3, "fga": 16, "fg_pct": 0.188, "fg3m": 1, "fg3a": 8, "fg3_pct": 0.125, "ftm": 9, "fta": 12, "ft_pct": 0.75, "oreb": 0, "dreb": 7, "reb": 7, "ast": 3, "stl": 2, "blk": 2, "tov": 3, "pf": 0, "pts": 16, "plus_minus": 7}, {"game_id": "0022200838", "game_date": "Feb 10, 2023", "matchup": "BOS vs. CHA", "wl": "W", "min": 37.0, "fgm": 13, "fga": 21, "fg_pct": 0.619, "fg3m": 5, "fg3a": 10, "fg3_pct": 0.5, "ftm": 10, "fta": 12, "ft_pct": 0.833, "oreb": 0, "dreb": 4, "reb": 4, "ast": 4, "stl": 1, "blk": 2, "tov": 4, "pf": 2, "pts": 41, "plus_minus": 2}, {"game_id": "0022200824", "game_date": "Feb 08, 2023", "matchup": "BOS vs. PHI", "wl": "W", "min": 37.0, "fgm": 5, "fga": 15, "fg_pct": 0.333, "fg3m": 1, "fg3a": 5, "fg3_pct": 0.2, "ftm": 1, "fta": 3, "ft_pct": 0.333, "oreb": 1, "dreb": 7, "reb": 8, "ast": 9, "stl": 1, "blk": 1, "tov": 4, "pf": 2, "pts": 12, "plus_minus": 5}, {"game_id": "0022200808", "game_date": "Feb 06, 2023", "matchup": "BOS @ DET", "wl": "W", "min": 39.0, "fgm": 11, "fga": 24, "fg_pct": 0.458, "fg3m": 3, "fg3a": 9, "fg3_pct": 0.333, "ftm": 9, "fta": 10, "ft_pct": 0.9, "oreb": 2, "dreb": 9, "reb": 11, "ast": 6, "stl": 0, "blk": 1, "tov": 3, "pf": 4, "pts": 34, "plus_minus": 16}, {"game_id": "0022200788", "game_date": "Feb 03, 2023", "matchup": "BOS vs. PHX", "wl": "L", "min": 38.0, "fgm": 3, "fga": 15, "fg_pct": 0.2, "fg3m": 3, "fg3a": 10, "fg3_pct": 0.3, "ftm": 11, "fta": 12, "ft_pct": 0.917, "oreb": 0, "dreb": 6, "reb": 6, "ast": 5, "stl": 0, "blk": 0, "tov": 2, "pf": 3, "pts": 20, "plus_minus": 1}, {"game_id": "0022200772", "game_date": "Feb 01, 2023", "matchup": "BOS vs. BKN", "wl": "W", "min": 29.0, "fgm": 12, "fga": 19, "fg_pct": 0.632, "fg3m": 7, "fg3a": 12, "fg3_pct": 0.583, "ftm": 0, "fta": 0, "ft_pct": 0.0, "oreb": 1, "dreb": 8, "reb": 9, "ast": 4, "stl": 2, "blk": 1, "tov": 1, "pf": 1, "pts": 31, "plus_minus": 46}, {"game_id": "0022200749", "game_date": "Jan 28, 2023", "matchup": "BOS vs. LAL", "wl": "W", "min": 47.0, "fgm": 8, "fga": 25, "fg_pct": 0.32, "fg3m": 3, "fg3a": 10, "fg3_pct": 0.3, "ftm": 11, "fta": 12, "ft_pct": 0.917, "oreb": 2, "dreb": 9, "reb": 11, "ast": 4, "stl": 2, "blk": 1, "tov": 6, "pf": 3, "pts": 30, "plus_minus": 2}, {"game_id": "0022200730", "game_date": "Jan 26, 2023", "matchup": "BOS vs. NYK", "wl": "L", "min": 43.0, "fgm": 12, "fga": 26, "fg_pct": 0.462, "fg3m": 2, "fg3a": 7, "fg3_pct": 0.286, "ftm": 9, "fta": 9, "ft_pct": 1.0, "oreb": 2, "dreb": 12, "reb": 14, "ast": 4, "stl": 1, "blk": 1, "tov": 3, "pf": 3, "pts": 35, "plus_minus": 6}, {"game_id": "0022200714", "game_date": "Jan 24, 2023", "matchup": "BOS @ MIA", "wl": "L", "min": 40.0, "fgm": 9, "fga": 18, "fg_pct": 0.5, "fg3m": 2, "fg3a": 5, "fg3_pct": 0.4, "ftm": 11, "fta": 14, "ft_pct": 0.786, "oreb": 0, "dreb": 14, "reb": 14, "ast": 7, "stl": 0, "blk": 0, "tov": 7, "pf": 4, "pts": 31, "plus_minus": -3}, {"game_id": "0022200707", "game_date": "Jan 23, 2023", "matchup": "BOS @ ORL", "wl": "L", "min": 38.0, "fgm": 9, "fga": 19, "fg_pct": 0.474, "fg3m": 4, "fg3a": 10, "fg3_pct": 0.4, "ftm": 4, "fta": 6, "ft_pct": 0.667, "oreb": 0, "dreb": 6, "reb": 6, "ast": 7, "stl": 1, "blk": 0, "tov": 3, "pf": 2, "pts": 26, "plus_minus": 6}, {"game_id": "0022200679", "game_date": "Jan 19, 2023", "matchup": "BOS vs. GSW", "wl": "W", "min": 48.0, "fgm": 9, "fga": 27, "fg_pct": 0.333, "fg3m": 4, "fg3a": 13, "fg3_pct": 0.308, "ftm": 12, "fta": 12, "ft_pct": 1.0, "oreb": 2, "dreb": 17, "reb": 19, "ast": 6, "stl": 3, "blk": 0, "tov": 7, "pf": 2, "pts": 34, "plus_minus": 7}, {"game_id": "0022200656", "game_date": "Jan 16, 2023", "matchup": "BOS @ CHA", "wl": "W", "min": 40.0, "fgm": 15, "fga": 23, "fg_pct": 0.652, "fg3m": 7, "fg3a": 12, "fg3_pct": 0.583, "ftm": 14, "fta": 14, "ft_pct": 1.0, "oreb": 1, "dreb": 8, "reb": 9, "ast": 5, "stl": 0, "blk": 0, "tov": 4, "pf": 3, "pts": 51, "plus_minus": 15}, {"game_id": "0022200642", "game_date": "Jan 14, 2023", "matchup": "BOS @ CHA", "wl": "W", "min": 37.0, "fgm": 12, "fga": 27, "fg_pct": 0.444, "fg3m": 4, "fg3a": 14, "fg3_pct": 0.286, "ftm": 5, "fta": 5, "ft_pct": 1.0, "oreb": 3, "dreb": 6, "reb": 9, "ast": 6, "stl": 0, "blk": 1, "tov": 1, "pf": 0, "pts": 33, "plus_minus": 26}, {"game_id": "0022200627", "game_date": "Jan 12, 2023", "matchup": "BOS @ BKN", "wl": "W", "min": 38.0, "fgm": 7, "fga": 22, "fg_pct": 0.318, "fg3m": 2, "fg3a": 10, "fg3_pct": 0.2, "ftm": 4, "fta": 4, "ft_pct": 1.0, "oreb": 0, "dreb": 11, "reb": 11, "ast": 5, "stl": 0, "blk": 1, "tov": 3, "pf": 3, "pts": 20, "plus_minus": 2}, {"game_id": "0022200621", "game_date": "Jan 11, 2023", "matchup": "BOS vs. NOP", "wl": "W", "min": 36.0, "fgm": 10, "fga": 22, "fg_pct": 0.455, "fg3m": 3, "fg3a": 8, "fg3_pct": 0.375, "ftm": 8, "fta": 10, "ft_pct": 0.8, "oreb": 2, "dreb": 8, "reb": 10, "ast": 4, "stl": 1, "blk": 0, "tov": 0, "pf": 2, "pts": 31, "plus_minus": 12}, {"game_id": "0022200606", "game_date": "Jan 09, 2023", "matchup": "BOS vs. CHI", "wl": "W", "min": 38.0, "fgm": 10, "fga": 21, "fg_pct": 0.476, "fg3m": 4, "fg3a": 11, "fg3_pct": 0.364, "ftm": 8, "fta": 8, "ft_pct": 1.0, "oreb": 0, "dreb": 8, "reb": 8, "ast": 7, "stl": 1, "blk": 0, "tov": 1, "pf": 2, "pts": 32, "plus_minus": 14}, {"game_id": "0022200591", "game_date": "Jan 07, 2023", "matchup": "BOS @ SAS", "wl": "W", "min": 36.0, "fgm": 13, "fga": 26, "fg_pct": 0.5, "fg3m": 5, "fg3a": 10, "fg3_pct": 0.5, "ftm": 3, "fta": 5, "ft_pct": 0.6, "oreb": 0, "dreb": 4, "reb": 4, "ast": 2, "stl": 0, "blk": 0, "tov": 2, "pf": 3, "pts": 34, "plus_minus": 2}, {"game_id": "0022200577", "game_date": "Jan 05, 2023", "matchup": "BOS @ DAL", "wl": "W", "min": 35.0, "fgm": 8, "fga": 22, "fg_pct": 0.364, "fg3m": 2, "fg3a": 8, "fg3_pct": 0.25, "ftm": 11, "fta": 12, "ft_pct": 0.917, "oreb": 2, "dreb": 12, "reb": 14, "ast": 10, "stl": 1, "blk": 2, "tov": 2, "pf": 2, "pts": 29, "plus_minus": 15}, {"game_id": "0022200562", "game_date": "Jan 03, 2023", "matchup": "BOS @ OKC", "wl": "L", "min": 30.0, "fgm": 9, "fga": 17, "fg_pct": 0.529, "fg3m": 2, "fg3a": 7, "fg3_pct": 0.286, "ftm": 7, "fta": 7, "ft_pct": 1.0, "oreb": 1, "dreb": 5, "reb": 6, "ast": 2, "stl": 0, "blk": 0, "tov": 4, "pf": 2, "pts": 27, "plus_minus": -25}, {"game_id": "0022200549", "game_date": "Jan 01, 2023", "matchup": "BOS @ DEN", "wl": "L", "min": 36.0, "fgm": 7, "fga": 16, "fg_pct": 0.438, "fg3m": 0, "fg3a": 4, "fg3_pct": 0.0, "ftm": 11, "fta": 14, "ft_pct": 0.786, "oreb": 0, "dreb": 7, "reb": 7, "ast": 6, "stl": 2, "blk": 0, "tov": 5, "pf": 1, "pts": 25, "plus_minus": -15}, {"game_id": "0022200525", "game_date": "Dec 29, 2022", "matchup": "BOS vs. LAC", "wl": "W", "min": 36.0, "fgm": 10, "fga": 26, "fg_pct": 0.385, "fg3m": 3, "fg3a": 11, "fg3_pct": 0.273, "ftm": 6, "fta": 10, "ft_pct": 0.6, "oreb": 1, "dreb": 10, "reb": 11, "ast": 1, "stl": 0, "blk": 1, "tov": 2, "pf": 2, "pts": 29, "plus_minus": -5}, {"game_id": "0022200507", "game_date": "Dec 27, 2022", "matchup": "BOS vs. HOU", "wl": "W", "min": 34.0, "fgm": 12, "fga": 25, "fg_pct": 0.48, "fg3m": 6, "fg3a": 16, "fg3_pct": 0.375, "ftm": 8, "fta": 8, "ft_pct": 1.0, "oreb": 0, "dreb": 8, "reb": 8, "ast": 4, "stl": 1, "blk": 1, "tov": 2, "pf": 2, "pts": 38, "plus_minus": 12}, {"game_id": "0022200495", "game_date": "Dec 25, 2022", "matchup": "BOS vs. MIL", "wl": "W", "min": 36.0, "fgm": 14, "fga": 22, "fg_pct": 0.636, "fg3m": 3, "fg3a": 7, "fg3_pct": 0.429, "ftm": 10, "fta": 10, "ft_pct": 1.0, "oreb": 0, "dreb": 7, "reb": 7, "ast": 5, "stl": 3, "blk": 0, "tov": 1, "pf": 3, "pts": 41, "plus_minus": 18}, {"game_id": "0022200482", "game_date": "Dec 23, 2022", "matchup": "BOS vs. MIN", "wl": "W", "min": 35.0, "fgm": 10, "fga": 22, "fg_pct": 0.455, "fg3m": 1, "fg3a": 6, "fg3_pct": 0.167, "ftm": 9, "fta": 11, "ft_pct": 0.818, "oreb": 2, "dreb": 6, "reb": 8, "ast": 5, "stl": 1, "blk": 0, "tov": 3, "pf": 3, "pts": 30, "plus_minus": 11}, {"game_id": "0022200469", "game_date": "Dec 21, 2022", "matchup": "BOS vs. IND", "wl": "L", "min": 41.0, "fgm": 13, "fga": 25, "fg_pct": 0.52, "fg3m": 4, "fg3a": 11, "fg3_pct": 0.364, "ftm": 11, "fta": 13, "ft_pct": 0.846, "oreb": 1, "dreb": 4, "reb": 5, "ast": 4, "stl": 2, "blk": 1, "tov": 2, "pf": 0, "pts": 41, "plus_minus": 4}, {"game_id": "0022200430", "game_date": "Dec 16, 2022", "matchup": "BOS vs. ORL", "wl": "L", "min": 38.0, "fgm": 9, "fga": 20, "fg_pct": 0.45, "fg3m": 2, "fg3a": 8, "fg3_pct": 0.25, "ftm": 11, "fta": 12, "ft_pct": 0.917, "oreb": 3, "dreb": 4, "reb": 7, "ast": 3, "stl": 2, "blk": 0, "tov": 2, "pf": 1, "pts": 31, "plus_minus": -10}, {"game_id": "0022200413", "game_date": "Dec 13, 2022", "matchup": "BOS @ LAL", "wl": "W", "min": 44.0, "fgm": 15, "fga": 29, "fg_pct": 0.517, "fg3m": 5, "fg3a": 10, "fg3_pct": 0.5, "ftm": 9, "fta": 10, "ft_pct": 0.9, "oreb": 1, "dreb": 8, "reb": 9, "ast": 6, "stl": 0, "blk": 1, "tov": 4, "pf": 1, "pts": 44, "plus_minus": 12}, {"game_id": "0022200408", "game_date": "Dec 12, 2022", "matchup": "BOS @ LAC", "wl": "L", "min": 37.0, "fgm": 7, "fga": 20, "fg_pct": 0.35, "fg3m": 2, "fg3a": 8, "fg3_pct": 0.25, "ftm": 4, "fta": 4, "ft_pct": 1.0, "oreb": 2, "dreb": 9, "reb": 11, "ast": 4, "stl": 1, "blk": 0, "tov": 3, "pf": 3, "pts": 20, "plus_minus": -18}, {"game_id": "0022200392", "game_date": "Dec 10, 2022", "matchup": "BOS @ GSW", "wl": "L", "min": 40.0, "fgm": 6, "fga": 21, "fg_pct": 0.286, "fg3m": 2, "fg3a": 9, "fg3_pct": 0.222, "ftm": 4, "fta": 7, "ft_pct": 0.571, "oreb": 1, "dreb": 6, "reb": 7, "ast": 2, "stl": 3, "blk": 1, "tov": 2, "pf": 2, "pts": 18, "plus_minus": -13}, {"game_id": "0022200373", "game_date": "Dec 07, 2022", "matchup": "BOS @ PHX", "wl": "W", "min": 29.0, "fgm": 9, "fga": 19, "fg_pct": 0.474, "fg3m": 3, "fg3a": 8, "fg3_pct": 0.375, "ftm": 4, "fta": 6, "ft_pct": 0.667, "oreb": 0, "dreb": 5, "reb": 5, "ast": 2, "stl": 2, "blk": 0, "tov": 3, "pf": 2, "pts": 25, "plus_minus": 26}, {"game_id": "0022200355", "game_date": "Dec 05, 2022", "matchup": "BOS @ TOR", "wl": "W", "min": 39.0, "fgm": 11, "fga": 24, "fg_pct": 0.458, "fg3m": 5, "fg3a": 10, "fg3_pct": 0.5, "ftm": 4, "fta": 5, "ft_pct": 0.8, "oreb": 3, "dreb": 9, "reb": 12, "ast": 3, "stl": 1, "blk": 1, "tov": 4, "pf": 2, "pts": 31, "plus_minus": 9}, {"game_id": "0022200346", "game_date": "Dec 04, 2022", "matchup": "BOS @ BKN", "wl": "W", "min": 37.0, "fgm": 10, "fga": 19, "fg_pct": 0.526, "fg3m": 3, "fg3a": 6, "fg3_pct": 0.5, "ftm": 6, "fta": 6, "ft_pct": 1.0, "oreb": 2, "dreb": 9, "reb": 11, "ast": 1, "stl": 4, "blk": 0, "tov": 9, "pf": 3, "pts": 29, "plus_minus": 12}, {"game_id": "0022200328", "game_date": "Dec 02, 2022", "matchup": "BOS vs. MIA", "wl": "L", "min": 41.0, "fgm": 5, "fga": 18, "fg_pct": 0.278, "fg3m": 0, "fg3a": 7, "fg3_pct": 0.0, "ftm": 4, "fta": 6, "ft_pct": 0.667, "oreb": 3, "dreb": 9, "reb": 12, "ast": 3, "stl": 0, "blk": 0, "tov": 5, "pf": 4, "pts": 14, "plus_minus": 0}, {"game_id": "0022200314", "game_date": "Nov 30, 2022", "matchup": "BOS vs. MIA", "wl": "W", "min": 39.0, "fgm": 15, "fga": 25, "fg_pct": 0.6, "fg3m": 8, "fg3a": 12, "fg3_pct": 0.667, "ftm": 11, "fta": 12, "ft_pct": 0.917, "oreb": 1, "dreb": 10, "reb": 11, "ast": 3, "stl": 2, "blk": 0, "tov": 1, "pf": 3, "pts": 49, "plus_minus": 29}, {"game_id": "0022200301", "game_date": "Nov 28, 2022", "matchup": "BOS vs. CHA", "wl": "W", "min": 30.0, "fgm": 15, "fga": 28, "fg_pct": 0.536, "fg3m": 4, "fg3a": 14, "fg3_pct": 0.286, "ftm": 1, "fta": 1, "ft_pct": 1.0, "oreb": 0, "dreb": 3, "reb": 3, "ast": 3, "stl": 2, "blk": 1, "tov": 0, "pf": 3, "pts": 35, "plus_minus": 45}, {"game_id": "0022200275", "game_date": "Nov 25, 2022", "matchup": "BOS vs. SAC", "wl": "W", "min": 31.0, "fgm": 10, "fga": 17, "fg_pct": 0.588, "fg3m": 2, "fg3a": 6, "fg3_pct": 0.333, "ftm": 8, "fta": 9, "ft_pct": 0.889, "oreb": 1, "dreb": 7, "reb": 8, "ast": 4, "stl": 1, "blk": 0, "tov": 3, "pf": 4, "pts": 30, "plus_minus": 12}, {"game_id": "0022200264", "game_date": "Nov 23, 2022", "matchup": "BOS vs. DAL", "wl": "W", "min": 37.0, "fgm": 11, "fga": 24, "fg_pct": 0.458, "fg3m": 2, "fg3a": 7, "fg3_pct": 0.286, "ftm": 13, "fta": 15, "ft_pct": 0.867, "oreb": 3, "dreb": 10, "reb": 13, "ast": 5, "stl": 0, "blk": 2, "tov": 2, "pf": 1, "pts": 37, "plus_minus": 14}, {"game_id": "0022200250", "game_date": "Nov 21, 2022", "matchup": "BOS @ CHI", "wl": "L", "min": 36.0, "fgm": 9, "fga": 19, "fg_pct": 0.474, "fg3m": 4, "fg3a": 10, "fg3_pct": 0.4, "ftm": 6, "fta": 7, "ft_pct": 0.857, "oreb": 2, "dreb": 9, "reb": 11, "ast": 7, "stl": 0, "blk": 0, "tov": 4, "pf": 1, "pts": 28, "plus_minus": -13}, {"game_id": "0022200231", "game_date": "Nov 18, 2022", "matchup": "BOS @ NOP", "wl": "W", "min": 39.0, "fgm": 6, "fga": 18, "fg_pct": 0.333, "fg3m": 2, "fg3a": 10, "fg3_pct": 0.2, "ftm": 5, "fta": 6, "ft_pct": 0.833, "oreb": 0, "dreb": 7, "reb": 7, "ast": 10, "stl": 0, "blk": 0, "tov": 3, "pf": 1, "pts": 19, "plus_minus": 11}, {"game_id": "0022200214", "game_date": "Nov 16, 2022", "matchup": "BOS @ ATL", "wl": "W", "min": 33.0, "fgm": 6, "fga": 19, "fg_pct": 0.316, "fg3m": 3, "fg3a": 10, "fg3_pct": 0.3, "ftm": 4, "fta": 4, "ft_pct": 1.0, "oreb": 1, "dreb": 6, "reb": 7, "ast": 8, "stl": 1, "blk": 1, "tov": 2, "pf": 1, "pts": 19, "plus_minus": 28}, {"game_id": "0022200201", "game_date": "Nov 14, 2022", "matchup": "BOS vs. OKC", "wl": "W", "min": 38.0, "fgm": 9, "fga": 23, "fg_pct": 0.391, "fg3m": 1, "fg3a": 9, "fg3_pct": 0.111, "ftm": 8, "fta": 10, "ft_pct": 0.8, "oreb": 1, "dreb": 9, "reb": 10, "ast": 1, "stl": 3, "blk": 3, "tov": 1, "pf": 2, "pts": 27, "plus_minus": 2}, {"game_id": "0022200186", "game_date": "Nov 12, 2022", "matchup": "BOS @ DET", "wl": "W", "min": 41.0, "fgm": 14, "fga": 28, "fg_pct": 0.5, "fg3m": 7, "fg3a": 14, "fg3_pct": 0.5, "ftm": 8, "fta": 10, "ft_pct": 0.8, "oreb": 2, "dreb": 8, "reb": 10, "ast": 3, "stl": 1, "blk": 1, "tov": 3, "pf": 2, "pts": 43, "plus_minus": 7}, {"game_id": "0022200176", "game_date": "Nov 11, 2022", "matchup": "BOS vs. DEN", "wl": "W", "min": 37.0, "fgm": 11, "fga": 21, "fg_pct": 0.524, "fg3m": 2, "fg3a": 7, "fg3_pct": 0.286, "ftm": 10, "fta": 11, "ft_pct": 0.909, "oreb": 0, "dreb": 8, "reb": 8, "ast": 5, "stl": 0, "blk": 0, "tov": 1, "pf": 4, "pts": 34, "plus_minus": 18}, {"game_id": "0022200163", "game_date": "Nov 09, 2022", "matchup": "BOS vs. DET", "wl": "W", "min": 32.0, "fgm": 10, "fga": 20, "fg_pct": 0.5, "fg3m": 5, "fg3a": 11, "fg3_pct": 0.455, "ftm": 6, "fta": 7, "ft_pct": 0.857, "oreb": 0, "dreb": 1, "reb": 1, "ast": 5, "stl": 1, "blk": 1, "tov": 1, "pf": 4, "pts": 31, "plus_minus": 16}, {"game_id": "0022200152", "game_date": "Nov 07, 2022", "matchup": "BOS @ MEM", "wl": "W", "min": 40.0, "fgm": 12, "fga": 25, "fg_pct": 0.48, "fg3m": 3, "fg3a": 11, "fg3_pct": 0.273, "ftm": 12, "fta": 16, "ft_pct": 0.75, "oreb": 0, "dreb": 3, "reb": 3, "ast": 2, "stl": 0, "blk": 2, "tov": 2, "pf": 2, "pts": 39, "plus_minus": 15}, {"game_id": "0022200135", "game_date": "Nov 05, 2022", "matchup": "BOS @ NYK", "wl": "W", "min": 37.0, "fgm": 8, "fga": 17, "fg_pct": 0.471, "fg3m": 6, "fg3a": 13, "fg3_pct": 0.462, "ftm": 4, "fta": 4, "ft_pct": 1.0, "oreb": 0, "dreb": 4, "reb": 4, "ast": 5, "stl": 1, "blk": 2, "tov": 3, "pf": 3, "pts": 26, "plus_minus": 2}, {"game_id": "0022200124", "game_date": "Nov 04, 2022", "matchup": "BOS vs. CHI", "wl": "W", "min": 40.0, "fgm": 8, "fga": 23, "fg_pct": 0.348, "fg3m": 3, "fg3a": 10, "fg3_pct": 0.3, "ftm": 17, "fta": 20, "ft_pct": 0.85, "oreb": 2, "dreb": 10, "reb": 12, "ast": 6, "stl": 1, "blk": 1, "tov": 1, "pf": 4, "pts": 36, "plus_minus": 11}, {"game_id": "0022200107", "game_date": "Nov 02, 2022", "matchup": "BOS @ CLE", "wl": "L", "min": 43.0, "fgm": 8, "fga": 21, "fg_pct": 0.381, "fg3m": 2, "fg3a": 9, "fg3_pct": 0.222, "ftm": 8, "fta": 8, "ft_pct": 1.0, "oreb": 3, "dreb": 9, "reb": 12, "ast": 6, "stl": 1, "blk": 4, "tov": 6, "pf": 0, "pts": 26, "plus_minus": -16}, {"game_id": "0022200089", "game_date": "Oct 30, 2022", "matchup": "BOS vs. WAS", "wl": "W", "min": 27.0, "fgm": 8, "fga": 15, "fg_pct": 0.533, "fg3m": 5, "fg3a": 10, "fg3_pct": 0.5, "ftm": 2, "fta": 2, "ft_pct": 1.0, "oreb": 0, "dreb": 4, "reb": 4, "ast": 3, "stl": 1, "blk": 0, "tov": 4, "pf": 0, "pts": 23, "plus_minus": 10}, {"game_id": "0022200072", "game_date": "Oct 28, 2022", "matchup": "BOS vs. CLE", "wl": "L", "min": 42.0, "fgm": 11, "fga": 19, "fg_pct": 0.579, "fg3m": 3, "fg3a": 7, "fg3_pct": 0.429, "ftm": 7, "fta": 8, "ft_pct": 0.875, "oreb": 1, "dreb": 6, "reb": 7, "ast": 4, "stl": 1, "blk": 1, "tov": 4, "pf": 4, "pts": 32, "plus_minus": -10}, {"game_id": "0022200047", "game_date": "Oct 24, 2022", "matchup": "BOS @ CHI", "wl": "L", "min": 35.0, "fgm": 8, "fga": 18, "fg_pct": 0.444, "fg3m": 4, "fg3a": 8, "fg3_pct": 0.5, "ftm": 6, "fta": 6, "ft_pct": 1.0, "oreb": 0, "dreb": 8, "reb": 8, "ast": 5, "stl": 0, "blk": 0, "tov": 1, "pf": 2, "pts": 26, "plus_minus": -8}, {"game_id": "0022200030", "game_date": "Oct 22, 2022", "matchup": "BOS @ ORL", "wl": "W", "min": 38.0, "fgm": 14, "fga": 21, "fg_pct": 0.667, "fg3m": 4, "fg3a": 10, "fg3_pct": 0.4, "ftm": 8, "fta": 9, "ft_pct": 0.889, "oreb": 0, "dreb": 8, "reb": 8, "ast": 1, "stl": 1, "blk": 2, "tov": 1, "pf": 2, "pts": 40, "plus_minus": 6}, {"game_id": "0022200022", "game_date": "Oct 21, 2022", "matchup": "BOS @ MIA", "wl": "W", "min": 37.0, "fgm": 10, "fga": 22, "fg_pct": 0.455, "fg3m": 2, "fg3a": 7, "fg3_pct": 0.286, "ftm": 7, "fta": 7, "ft_pct": 1.0, "oreb": 2, "dreb": 3, "reb": 5, "ast": 4, "stl": 1, "blk": 2, "tov": 2, "pf": 1, "pts": 29, "plus_minus": -1}, {"game_id": "0022200001", "game_date": "Oct 18, 2022", "matchup": "BOS vs. PHI", "wl": "W", "min": 39.0, "fgm": 13, "fga": 20, "fg_pct": 0.65, "fg3m": 2, "fg3a": 7, "fg3_pct": 0.286, "ftm": 7, "fta": 9, "ft_pct": 0.778, "oreb": 0, "dreb": 12, "reb": 12, "ast": 4, "stl": 1, "blk": 1, "tov": 3, "pf": 1, "pts": 35, "plus_minus": 10}]