[{"season_id": "22024", "player_id": 1641816, "game_id": "0022401193", "game_date": "Apr 13, 2025", "matchup": "DEN @ HOU", "wl": "W", "min": 4, "fgm": 0, "fga": 1, "fg_pct": 0.0, "fg3m": 0, "fg3a": 0, "fg3_pct": 0.0, "ftm": 2, "fta": 2, "ft_pct": 1.0, "oreb": 0, "dreb": 0, "reb": 0, "ast": 1, "stl": 0, "blk": 0, "tov": 0, "pf": 2, "pts": 2, "plus_minus": -13, "video_available": 1}, {"season_id": "22024", "player_id": 1641816, "game_id": "0022401125", "game_date": "Apr 04, 2025", "matchup": "DEN @ GSW", "wl": "L", "min": 1, "fgm": 0, "fga": 0, "fg_pct": 0.0, "fg3m": 0, "fg3a": 0, "fg3_pct": 0.0, "ftm": 0, "fta": 0, "ft_pct": 0.0, "oreb": 0, "dreb": 0, "reb": 0, "ast": 0, "stl": 1, "blk": 0, "tov": 0, "pf": 0, "pts": 0, "plus_minus": 0, "video_available": 1}, {"season_id": "22024", "player_id": 1641816, "game_id": "0022401110", "game_date": "Apr 02, 2025", "matchup": "DEN vs. SAS", "wl": "L", "min": 30, "fgm": 7, "fga": 20, "fg_pct": 0.35, "fg3m": 3, "fg3a": 9, "fg3_pct": 0.333, "ftm": 1, "fta": 1, "ft_pct": 1.0, "oreb": 3, "dreb": 3, "reb": 6, "ast": 0, "stl": 0, "blk": 0, "tov": 0, "pf": 0, "pts": 18, "plus_minus": -7, "video_available": 1}, {"season_id": "22024", "player_id": 1641816, "game_id": "0022401102", "game_date": "Apr 01, 2025", "matchup": "DEN vs. MIN", "wl": "L", "min": 5, "fgm": 0, "fga": 0, "fg_pct": 0.0, "fg3m": 0, "fg3a": 0, "fg3_pct": 0.0, "ftm": 0, "fta": 0, "ft_pct": 0.0, "oreb": 0, "dreb": 0, "reb": 0, "ast": 0, "stl": 1, "blk": 0, "tov": 0, "pf": 1, "pts": 0, "plus_minus": -3, "video_available": 1}, {"season_id": "22024", "player_id": 1641816, "game_id": "0022401073", "game_date": "Mar 28, 2025", "matchup": "DEN vs. UTA", "wl": "W", "min": 7, "fgm": 1, "fga": 3, "fg_pct": 0.333, "fg3m": 1, "fg3a": 3, "fg3_pct": 0.333, "ftm": 0, "fta": 0, "ft_pct": 0.0, "oreb": 0, "dreb": 1, "reb": 1, "ast": 1, "stl": 0, "blk": 1, "tov": 0, "pf": 1, "pts": 3, "plus_minus": 1, "video_available": 1}, {"season_id": "22024", "player_id": 1641816, "game_id": "0022401022", "game_date": "Mar 21, 2025", "matchup": "DEN @ POR", "wl": "L", "min": 4, "fgm": 1, "fga": 2, "fg_pct": 0.5, "fg3m": 1, "fg3a": 1, "fg3_pct": 1.0, "ftm": 0, "fta": 0, "ft_pct": 0.0, "oreb": 3, "dreb": 0, "reb": 3, "ast": 1, "stl": 0, "blk": 0, "tov": 0, "pf": 0, "pts": 3, "plus_minus": 3, "video_available": 1}, {"season_id": "22024", "player_id": 1641816, "game_id": "0022401006", "game_date": "Mar 19, 2025", "matchup": "DEN @ LAL", "wl": "L", "min": 12, "fgm": 2, "fga": 6, "fg_pct": 0.333, "fg3m": 0, "fg3a": 4, "fg3_pct": 0.0, "ftm": 2, "fta": 2, "ft_pct": 1.0, "oreb": 1, "dreb": 0, "reb": 1, "ast": 1, "stl": 0, "blk": 0, "tov": 1, "pf": 0, "pts": 6, "plus_minus": 14, "video_available": 1}, {"season_id": "22024", "player_id": 1641816, "game_id": "0022400990", "game_date": "Mar 17, 2025", "matchup": "DEN @ GSW", "wl": "W", "min": 20, "fgm": 4, "fga": 9, "fg_pct": 0.444, "fg3m": 1, "fg3a": 4, "fg3_pct": 0.25, "ftm": 0, "fta": 0, "ft_pct": 0.0, "oreb": 4, "dreb": 3, "reb": 7, "ast": 2, "stl": 2, "blk": 0, "tov": 0, "pf": 3, "pts": 9, "plus_minus": -3, "video_available": 1}, {"season_id": "22024", "player_id": 1641816, "game_id": "0022400952", "game_date": "Mar 12, 2025", "matchup": "DEN vs. MIN", "wl": "L", "min": 5, "fgm": 3, "fga": 5, "fg_pct": 0.6, "fg3m": 2, "fg3a": 4, "fg3_pct": 0.5, "ftm": 0, "fta": 0, "ft_pct": 0.0, "oreb": 0, "dreb": 0, "reb": 0, "ast": 0, "stl": 1, "blk": 0, "tov": 0, "pf": 0, "pts": 8, "plus_minus": 6, "video_available": 1}, {"season_id": "22024", "player_id": 1641816, "game_id": "0022400920", "game_date": "Mar 09, 2025", "matchup": "DEN @ OKC", "wl": "L", "min": 1, "fgm": 0, "fga": 0, "fg_pct": 0.0, "fg3m": 0, "fg3a": 0, "fg3_pct": 0.0, "ftm": 0, "fta": 0, "ft_pct": 0.0, "oreb": 0, "dreb": 0, "reb": 0, "ast": 0, "stl": 0, "blk": 0, "tov": 0, "pf": 0, "pts": 0, "plus_minus": -2, "video_available": 1}, {"season_id": "22024", "player_id": 1641816, "game_id": "0022400850", "game_date": "Feb 28, 2025", "matchup": "DEN @ DET", "wl": "W", "min": 4, "fgm": 0, "fga": 0, "fg_pct": 0.0, "fg3m": 0, "fg3a": 0, "fg3_pct": 0.0, "ftm": 0, "fta": 0, "ft_pct": 0.0, "oreb": 0, "dreb": 0, "reb": 0, "ast": 0, "stl": 0, "blk": 0, "tov": 0, "pf": 1, "pts": 0, "plus_minus": -9, "video_available": 1}, {"season_id": "22024", "player_id": 1641816, "game_id": "0022400808", "game_date": "Feb 22, 2025", "matchup": "DEN vs. LAL", "wl": "L", "min": 8, "fgm": 0, "fga": 2, "fg_pct": 0.0, "fg3m": 0, "fg3a": 2, "fg3_pct": 0.0, "ftm": 0, "fta": 0, "ft_pct": 0.0, "oreb": 1, "dreb": 0, "reb": 1, "ast": 0, "stl": 0, "blk": 0, "tov": 0, "pf": 2, "pts": 0, "plus_minus": -2, "video_available": 1}, {"season_id": "22024", "player_id": 1641816, "game_id": "0022400780", "game_date": "Feb 12, 2025", "matchup": "DEN vs. POR", "wl": "W", "min": 6, "fgm": 0, "fga": 2, "fg_pct": 0.0, "fg3m": 0, "fg3a": 1, "fg3_pct": 0.0, "ftm": 0, "fta": 0, "ft_pct": 0.0, "oreb": 0, "dreb": 0, "reb": 0, "ast": 0, "stl": 0, "blk": 0, "tov": 0, "pf": 0, "pts": 0, "plus_minus": -7, "video_available": 1}, {"season_id": "22024", "player_id": 1641816, "game_id": "0022400763", "game_date": "Feb 10, 2025", "matchup": "DEN vs. POR", "wl": "W", "min": 10, "fgm": 0, "fga": 3, "fg_pct": 0.0, "fg3m": 0, "fg3a": 3, "fg3_pct": 0.0, "ftm": 0, "fta": 0, "ft_pct": 0.0, "oreb": 2, "dreb": 1, "reb": 3, "ast": 1, "stl": 0, "blk": 0, "tov": 1, "pf": 2, "pts": 0, "plus_minus": -7, "video_available": 1}, {"season_id": "22024", "player_id": 1641816, "game_id": "0022400749", "game_date": "Feb 08, 2025", "matchup": "DEN @ PHX", "wl": "W", "min": 7, "fgm": 2, "fga": 2, "fg_pct": 1.0, "fg3m": 1, "fg3a": 1, "fg3_pct": 1.0, "ftm": 0, "fta": 0, "ft_pct": 0.0, "oreb": 0, "dreb": 0, "reb": 0, "ast": 0, "stl": 0, "blk": 0, "tov": 0, "pf": 0, "pts": 5, "plus_minus": -3, "video_available": 1}, {"season_id": "22024", "player_id": 1641816, "game_id": "0022400730", "game_date": "Feb 06, 2025", "matchup": "DEN vs. ORL", "wl": "W", "min": 11, "fgm": 2, "fga": 4, "fg_pct": 0.5, "fg3m": 2, "fg3a": 4, "fg3_pct": 0.5, "ftm": 1, "fta": 2, "ft_pct": 0.5, "oreb": 0, "dreb": 2, "reb": 2, "ast": 0, "stl": 0, "blk": 0, "tov": 3, "pf": 1, "pts": 7, "plus_minus": -6, "video_available": 1}, {"season_id": "22024", "player_id": 1641816, "game_id": "0022400726", "game_date": "Feb 05, 2025", "matchup": "DEN vs. NOP", "wl": "W", "min": 10, "fgm": 1, "fga": 2, "fg_pct": 0.5, "fg3m": 1, "fg3a": 2, "fg3_pct": 0.5, "ftm": 1, "fta": 2, "ft_pct": 0.5, "oreb": 0, "dreb": 2, "reb": 2, "ast": 0, "stl": 0, "blk": 0, "tov": 0, "pf": 0, "pts": 4, "plus_minus": -13, "video_available": 1}, {"season_id": "22024", "player_id": 1641816, "game_id": "0022400706", "game_date": "Feb 03, 2025", "matchup": "DEN vs. NOP", "wl": "W", "min": 9, "fgm": 0, "fga": 0, "fg_pct": 0.0, "fg3m": 0, "fg3a": 0, "fg3_pct": 0.0, "ftm": 0, "fta": 0, "ft_pct": 0.0, "oreb": 0, "dreb": 2, "reb": 2, "ast": 0, "stl": 0, "blk": 1, "tov": 0, "pf": 0, "pts": 0, "plus_minus": 2, "video_available": 1}, {"season_id": "22024", "player_id": 1641816, "game_id": "0022400634", "game_date": "Jan 25, 2025", "matchup": "DEN @ MIN", "wl": "L", "min": 5, "fgm": 0, "fga": 3, "fg_pct": 0.0, "fg3m": 0, "fg3a": 2, "fg3_pct": 0.0, "ftm": 0, "fta": 2, "ft_pct": 0.0, "oreb": 1, "dreb": 3, "reb": 4, "ast": 0, "stl": 1, "blk": 0, "tov": 0, "pf": 0, "pts": 0, "plus_minus": -4, "video_available": 1}, {"season_id": "22024", "player_id": 1641816, "game_id": "0022400609", "game_date": "Jan 21, 2025", "matchup": "DEN vs. PHI", "wl": "W", "min": 6, "fgm": 1, "fga": 4, "fg_pct": 0.25, "fg3m": 1, "fg3a": 3, "fg3_pct": 0.333, "ftm": 0, "fta": 0, "ft_pct": 0.0, "oreb": 0, "dreb": 2, "reb": 2, "ast": 1, "stl": 0, "blk": 0, "tov": 0, "pf": 0, "pts": 3, "plus_minus": 8, "video_available": 1}, {"season_id": "22024", "player_id": 1641816, "game_id": "0022400593", "game_date": "Jan 19, 2025", "matchup": "DEN @ ORL", "wl": "W", "min": 2, "fgm": 0, "fga": 2, "fg_pct": 0.0, "fg3m": 0, "fg3a": 2, "fg3_pct": 0.0, "ftm": 0, "fta": 0, "ft_pct": 0.0, "oreb": 0, "dreb": 0, "reb": 0, "ast": 0, "stl": 0, "blk": 0, "tov": 0, "pf": 0, "pts": 0, "plus_minus": -2, "video_available": 1}, {"season_id": "22024", "player_id": 1641816, "game_id": "0022400579", "game_date": "Jan 17, 2025", "matchup": "DEN @ MIA", "wl": "W", "min": 2, "fgm": 1, "fga": 1, "fg_pct": 1.0, "fg3m": 1, "fg3a": 1, "fg3_pct": 1.0, "ftm": 0, "fta": 0, "ft_pct": 0.0, "oreb": 0, "dreb": 0, "reb": 0, "ast": 0, "stl": 0, "blk": 0, "tov": 0, "pf": 0, "pts": 3, "plus_minus": -1, "video_available": 1}, {"season_id": "22024", "player_id": 1641816, "game_id": "0022400568", "game_date": "Jan 15, 2025", "matchup": "DEN vs. HOU", "wl": "L", "min": 8, "fgm": 1, "fga": 3, "fg_pct": 0.333, "fg3m": 1, "fg3a": 2, "fg3_pct": 0.5, "ftm": 1, "fta": 2, "ft_pct": 0.5, "oreb": 1, "dreb": 1, "reb": 2, "ast": 0, "stl": 0, "blk": 0, "tov": 0, "pf": 1, "pts": 4, "plus_minus": 2, "video_available": 1}, {"season_id": "22024", "player_id": 1641816, "game_id": "0022400559", "game_date": "Jan 14, 2025", "matchup": "DEN @ DAL", "wl": "W", "min": 3, "fgm": 0, "fga": 0, "fg_pct": 0.0, "fg3m": 0, "fg3a": 0, "fg3_pct": 0.0, "ftm": 0, "fta": 0, "ft_pct": 0.0, "oreb": 0, "dreb": 1, "reb": 1, "ast": 1, "stl": 0, "blk": 0, "tov": 0, "pf": 3, "pts": 0, "plus_minus": -4, "video_available": 1}, {"season_id": "22024", "player_id": 1641816, "game_id": "0022400531", "game_date": "Jan 10, 2025", "matchup": "DEN vs. BKN", "wl": "W", "min": 1, "fgm": 0, "fga": 0, "fg_pct": 0.0, "fg3m": 0, "fg3a": 0, "fg3_pct": 0.0, "ftm": 0, "fta": 0, "ft_pct": 0.0, "oreb": 0, "dreb": 0, "reb": 0, "ast": 0, "stl": 0, "blk": 0, "tov": 0, "pf": 0, "pts": 0, "plus_minus": -3, "video_available": 1}, {"season_id": "22024", "player_id": 1641816, "game_id": "0022400515", "game_date": "Jan 08, 2025", "matchup": "DEN vs. LAC", "wl": "W", "min": 9, "fgm": 0, "fga": 1, "fg_pct": 0.0, "fg3m": 0, "fg3a": 0, "fg3_pct": 0.0, "ftm": 0, "fta": 0, "ft_pct": 0.0, "oreb": 0, "dreb": 1, "reb": 1, "ast": 0, "stl": 0, "blk": 0, "tov": 0, "pf": 3, "pts": 0, "plus_minus": -1, "video_available": 1}, {"season_id": "22024", "player_id": 1641816, "game_id": "0022400507", "game_date": "Jan 07, 2025", "matchup": "DEN vs. BOS", "wl": "L", "min": 0, "fgm": 0, "fga": 0, "fg_pct": 0.0, "fg3m": 0, "fg3a": 0, "fg3_pct": 0.0, "ftm": 0, "fta": 0, "ft_pct": 0.0, "oreb": 0, "dreb": 0, "reb": 0, "ast": 0, "stl": 0, "blk": 0, "tov": 0, "pf": 0, "pts": 0, "plus_minus": 0, "video_available": 1}, {"season_id": "22024", "player_id": 1641816, "game_id": "0022400484", "game_date": "Jan 04, 2025", "matchup": "DEN @ SAS", "wl": "W", "min": 1, "fgm": 0, "fga": 0, "fg_pct": 0.0, "fg3m": 0, "fg3a": 0, "fg3_pct": 0.0, "ftm": 0, "fta": 0, "ft_pct": 0.0, "oreb": 0, "dreb": 0, "reb": 0, "ast": 0, "stl": 0, "blk": 0, "tov": 0, "pf": 1, "pts": 0, "plus_minus": -3, "video_available": 1}, {"season_id": "22024", "player_id": 1641816, "game_id": "0022400475", "game_date": "Jan 03, 2025", "matchup": "DEN vs. SAS", "wl": "L", "min": 5, "fgm": 0, "fga": 1, "fg_pct": 0.0, "fg3m": 0, "fg3a": 1, "fg3_pct": 0.0, "ftm": 0, "fta": 0, "ft_pct": 0.0, "oreb": 0, "dreb": 1, "reb": 1, "ast": 0, "stl": 0, "blk": 1, "tov": 0, "pf": 0, "pts": 0, "plus_minus": -11, "video_available": 1}, {"season_id": "22024", "player_id": 1641816, "game_id": "0022400461", "game_date": "Jan 01, 2025", "matchup": "DEN vs. ATL", "wl": "W", "min": 4, "fgm": 0, "fga": 0, "fg_pct": 0.0, "fg3m": 0, "fg3a": 0, "fg3_pct": 0.0, "ftm": 0, "fta": 0, "ft_pct": 0.0, "oreb": 0, "dreb": 0, "reb": 0, "ast": 0, "stl": 0, "blk": 0, "tov": 0, "pf": 0, "pts": 0, "plus_minus": -3, "video_available": 1}, {"season_id": "22024", "player_id": 1641816, "game_id": "0022400445", "game_date": "Dec 30, 2024", "matchup": "DEN @ UTA", "wl": "W", "min": 7, "fgm": 0, "fga": 2, "fg_pct": 0.0, "fg3m": 0, "fg3a": 2, "fg3_pct": 0.0, "ftm": 0, "fta": 0, "ft_pct": 0.0, "oreb": 0, "dreb": 0, "reb": 0, "ast": 0, "stl": 0, "blk": 0, "tov": 0, "pf": 1, "pts": 0, "plus_minus": -6, "video_available": 1}, {"season_id": "22024", "player_id": 1641816, "game_id": "0022400432", "game_date": "Dec 28, 2024", "matchup": "DEN vs. DET", "wl": "W", "min": 13, "fgm": 1, "fga": 3, "fg_pct": 0.333, "fg3m": 0, "fg3a": 1, "fg3_pct": 0.0, "ftm": 0, "fta": 0, "ft_pct": 0.0, "oreb": 1, "dreb": 2, "reb": 3, "ast": 2, "stl": 0, "blk": 0, "tov": 1, "pf": 0, "pts": 2, "plus_minus": 8, "video_available": 1}, {"season_id": "22024", "player_id": 1641816, "game_id": "0022400424", "game_date": "Dec 27, 2024", "matchup": "DEN vs. CLE", "wl": "L", "min": 6, "fgm": 1, "fga": 3, "fg_pct": 0.333, "fg3m": 1, "fg3a": 1, "fg3_pct": 1.0, "ftm": 0, "fta": 0, "ft_pct": 0.0, "oreb": 0, "dreb": 1, "reb": 1, "ast": 0, "stl": 0, "blk": 0, "tov": 0, "pf": 1, "pts": 3, "plus_minus": -2, "video_available": 1}, {"season_id": "22024", "player_id": 1641816, "game_id": "0022400402", "game_date": "Dec 23, 2024", "matchup": "DEN vs. PHX", "wl": "W", "min": 16, "fgm": 2, "fga": 4, "fg_pct": 0.5, "fg3m": 1, "fg3a": 2, "fg3_pct": 0.5, "ftm": 1, "fta": 2, "ft_pct": 0.5, "oreb": 0, "dreb": 4, "reb": 4, "ast": 0, "stl": 1, "blk": 0, "tov": 0, "pf": 2, "pts": 6, "plus_minus": 3, "video_available": 1}, {"season_id": "22024", "player_id": 1641816, "game_id": "0022400371", "game_date": "Dec 19, 2024", "matchup": "DEN @ POR", "wl": "L", "min": 6, "fgm": 0, "fga": 2, "fg_pct": 0.0, "fg3m": 0, "fg3a": 1, "fg3_pct": 0.0, "ftm": 0, "fta": 0, "ft_pct": 0.0, "oreb": 1, "dreb": 1, "reb": 2, "ast": 1, "stl": 0, "blk": 0, "tov": 0, "pf": 0, "pts": 0, "plus_minus": 8, "video_available": 1}, {"season_id": "22024", "player_id": 1641816, "game_id": "0022401225", "game_date": "Dec 16, 2024", "matchup": "DEN @ SAC", "wl": "W", "min": 17, "fgm": 2, "fga": 2, "fg_pct": 1.0, "fg3m": 1, "fg3a": 1, "fg3_pct": 1.0, "ftm": 2, "fta": 2, "ft_pct": 1.0, "oreb": 1, "dreb": 2, "reb": 3, "ast": 1, "stl": 1, "blk": 0, "tov": 1, "pf": 3, "pts": 7, "plus_minus": -7, "video_available": 1}, {"season_id": "22024", "player_id": 1641816, "game_id": "0022401213", "game_date": "Dec 13, 2024", "matchup": "DEN vs. LAC", "wl": "W", "min": 5, "fgm": 1, "fga": 1, "fg_pct": 1.0, "fg3m": 1, "fg3a": 1, "fg3_pct": 1.0, "ftm": 2, "fta": 2, "ft_pct": 1.0, "oreb": 0, "dreb": 1, "reb": 1, "ast": 0, "stl": 0, "blk": 0, "tov": 2, "pf": 1, "pts": 5, "plus_minus": 0, "video_available": 1}, {"season_id": "22024", "player_id": 1641816, "game_id": "0022400350", "game_date": "Dec 08, 2024", "matchup": "DEN @ ATL", "wl": "W", "min": 8, "fgm": 2, "fga": 2, "fg_pct": 1.0, "fg3m": 1, "fg3a": 1, "fg3_pct": 1.0, "ftm": 0, "fta": 0, "ft_pct": 0.0, "oreb": 0, "dreb": 1, "reb": 1, "ast": 1, "stl": 0, "blk": 0, "tov": 0, "pf": 1, "pts": 5, "plus_minus": 7, "video_available": 1}, {"season_id": "22024", "player_id": 1641816, "game_id": "0022400341", "game_date": "Dec 07, 2024", "matchup": "DEN @ WAS", "wl": "L", "min": 12, "fgm": 0, "fga": 2, "fg_pct": 0.0, "fg3m": 0, "fg3a": 2, "fg3_pct": 0.0, "ftm": 2, "fta": 2, "ft_pct": 1.0, "oreb": 2, "dreb": 2, "reb": 4, "ast": 0, "stl": 0, "blk": 0, "tov": 0, "pf": 0, "pts": 2, "plus_minus": -5, "video_available": 1}, {"season_id": "22024", "player_id": 1641816, "game_id": "0022400298", "game_date": "Nov 27, 2024", "matchup": "DEN @ UTA", "wl": "W", "min": 16, "fgm": 1, "fga": 3, "fg_pct": 0.333, "fg3m": 1, "fg3a": 2, "fg3_pct": 0.5, "ftm": 2, "fta": 2, "ft_pct": 1.0, "oreb": 0, "dreb": 4, "reb": 4, "ast": 0, "stl": 0, "blk": 2, "tov": 2, "pf": 2, "pts": 5, "plus_minus": -5, "video_available": 1}, {"season_id": "22024", "player_id": 1641816, "game_id": "0022400283", "game_date": "Nov 25, 2024", "matchup": "DEN vs. NYK", "wl": "L", "min": 10, "fgm": 2, "fga": 3, "fg_pct": 0.667, "fg3m": 1, "fg3a": 2, "fg3_pct": 0.5, "ftm": 0, "fta": 0, "ft_pct": 0.0, "oreb": 1, "dreb": 0, "reb": 1, "ast": 1, "stl": 0, "blk": 0, "tov": 0, "pf": 1, "pts": 5, "plus_minus": -4, "video_available": 1}, {"season_id": "22024", "player_id": 1641816, "game_id": "0022400270", "game_date": "Nov 23, 2024", "matchup": "DEN @ LAL", "wl": "W", "min": 3, "fgm": 0, "fga": 0, "fg_pct": 0.0, "fg3m": 0, "fg3a": 0, "fg3_pct": 0.0, "ftm": 1, "fta": 2, "ft_pct": 0.5, "oreb": 1, "dreb": 1, "reb": 2, "ast": 1, "stl": 0, "blk": 0, "tov": 0, "pf": 0, "pts": 1, "plus_minus": -2, "video_available": 1}, {"season_id": "22024", "player_id": 1641816, "game_id": "0022400033", "game_date": "Nov 22, 2024", "matchup": "DEN vs. DAL", "wl": "L", "min": 2, "fgm": 0, "fga": 1, "fg_pct": 0.0, "fg3m": 0, "fg3a": 0, "fg3_pct": 0.0, "ftm": 0, "fta": 0, "ft_pct": 0.0, "oreb": 0, "dreb": 0, "reb": 0, "ast": 0, "stl": 0, "blk": 0, "tov": 0, "pf": 0, "pts": 0, "plus_minus": -1, "video_available": 1}, {"season_id": "22024", "player_id": 1641816, "game_id": "0022400238", "game_date": "Nov 17, 2024", "matchup": "DEN @ MEM", "wl": "L", "min": 1, "fgm": 0, "fga": 1, "fg_pct": 0.0, "fg3m": 0, "fg3a": 1, "fg3_pct": 0.0, "ftm": 0, "fta": 0, "ft_pct": 0.0, "oreb": 0, "dreb": 0, "reb": 0, "ast": 0, "stl": 0, "blk": 0, "tov": 0, "pf": 0, "pts": 0, "plus_minus": 0, "video_available": 1}, {"season_id": "22024", "player_id": 1641816, "game_id": "0022400017", "game_date": "Nov 15, 2024", "matchup": "DEN @ NOP", "wl": "L", "min": 2, "fgm": 0, "fga": 2, "fg_pct": 0.0, "fg3m": 0, "fg3a": 2, "fg3_pct": 0.0, "ftm": 0, "fta": 0, "ft_pct": 0.0, "oreb": 0, "dreb": 0, "reb": 0, "ast": 0, "stl": 0, "blk": 0, "tov": 0, "pf": 0, "pts": 0, "plus_minus": -7, "video_available": 1}, {"season_id": "22024", "player_id": 1641816, "game_id": "0022400194", "game_date": "Nov 08, 2024", "matchup": "DEN vs. MIA", "wl": "W", "min": 9, "fgm": 3, "fga": 3, "fg_pct": 1.0, "fg3m": 1, "fg3a": 1, "fg3_pct": 1.0, "ftm": 0, "fta": 0, "ft_pct": 0.0, "oreb": 1, "dreb": 1, "reb": 2, "ast": 0, "stl": 0, "blk": 0, "tov": 1, "pf": 2, "pts": 7, "plus_minus": -12, "video_available": 1}, {"season_id": "22024", "player_id": 1641816, "game_id": "0022400177", "game_date": "Nov 06, 2024", "matchup": "DEN vs. OKC", "wl": "W", "min": 19, "fgm": 1, "fga": 2, "fg_pct": 0.5, "fg3m": 0, "fg3a": 1, "fg3_pct": 0.0, "ftm": 0, "fta": 0, "ft_pct": 0.0, "oreb": 0, "dreb": 4, "reb": 4, "ast": 0, "stl": 1, "blk": 0, "tov": 2, "pf": 4, "pts": 2, "plus_minus": -6, "video_available": 1}, {"season_id": "22024", "player_id": 1641816, "game_id": "0022400166", "game_date": "Nov 04, 2024", "matchup": "DEN vs. TOR", "wl": "W", "min": 15, "fgm": 0, "fga": 1, "fg_pct": 0.0, "fg3m": 0, "fg3a": 1, "fg3_pct": 0.0, "ftm": 0, "fta": 0, "ft_pct": 0.0, "oreb": 0, "dreb": 1, "reb": 1, "ast": 0, "stl": 1, "blk": 1, "tov": 0, "pf": 2, "pts": 0, "plus_minus": -2, "video_available": 1}, {"season_id": "22024", "player_id": 1641816, "game_id": "0022400148", "game_date": "Nov 02, 2024", "matchup": "DEN vs. UTA", "wl": "W", "min": 25, "fgm": 2, "fga": 5, "fg_pct": 0.4, "fg3m": 0, "fg3a": 2, "fg3_pct": 0.0, "ftm": 3, "fta": 3, "ft_pct": 1.0, "oreb": 1, "dreb": 3, "reb": 4, "ast": 4, "stl": 0, "blk": 0, "tov": 0, "pf": 2, "pts": 7, "plus_minus": 5, "video_available": 1}, {"season_id": "22024", "player_id": 1641816, "game_id": "0022400139", "game_date": "Nov 01, 2024", "matchup": "DEN @ MIN", "wl": "L", "min": 6, "fgm": 1, "fga": 1, "fg_pct": 1.0, "fg3m": 0, "fg3a": 0, "fg3_pct": 0.0, "ftm": 0, "fta": 0, "ft_pct": 0.0, "oreb": 0, "dreb": 1, "reb": 1, "ast": 0, "stl": 0, "blk": 0, "tov": 0, "pf": 1, "pts": 2, "plus_minus": 1, "video_available": 1}, {"season_id": "22024", "player_id": 1641816, "game_id": "0022400075", "game_date": "Oct 24, 2024", "matchup": "DEN vs. OKC", "wl": "L", "min": 2, "fgm": 0, "fga": 1, "fg_pct": 0.0, "fg3m": 0, "fg3a": 1, "fg3_pct": 0.0, "ftm": 0, "fta": 0, "ft_pct": 0.0, "oreb": 0, "dreb": 1, "reb": 1, "ast": 0, "stl": 0, "blk": 0, "tov": 0, "pf": 0, "pts": 0, "plus_minus": 0, "video_available": 1}]