[{"player_id": 1630579, "game_id": "0022400004", "period": 1, "action_type": "Tip Dunk Shot", "shot_zone_basic": "Restricted Area", "shot_zone_area": "Center(C)", "shot_distance": 0, "loc_x": 0, "loc_y": 0, "shot_made_flag": 1, "game_date": "20241112", "htm": "PHI", "vtm": "NYK", "minutes_remaining": 2, "seconds_remaining": 38}, {"player_id": 1630579, "game_id": "0022400014", "period": 1, "action_type": "Alley Oop Dunk Shot", "shot_zone_basic": "Restricted Area", "shot_zone_area": "Center(C)", "shot_distance": 0, "loc_x": 1, "loc_y": 7, "shot_made_flag": 1, "game_date": "20241115", "htm": "NYK", "vtm": "BKN", "minutes_remaining": 7, "seconds_remaining": 20}, {"player_id": 1630579, "game_id": "0022400014", "period": 1, "action_type": "Cutting Dunk Shot", "shot_zone_basic": "Restricted Area", "shot_zone_area": "Center(C)", "shot_distance": 0, "loc_x": 7, "loc_y": 6, "shot_made_flag": 0, "game_date": "20241115", "htm": "NYK", "vtm": "BKN", "minutes_remaining": 5, "seconds_remaining": 39}, {"player_id": 1630579, "game_id": "0022400014", "period": 1, "action_type": "Putback Layup Shot", "shot_zone_basic": "Restricted Area", "shot_zone_area": "Center(C)", "shot_distance": 0, "loc_x": 0, "loc_y": 0, "shot_made_flag": 1, "game_date": "20241115", "htm": "NYK", "vtm": "BKN", "minutes_remaining": 5, "seconds_remaining": 36}, {"player_id": 1630579, "game_id": "0022400053", "period": 4, "action_type": "Cutting Dunk Shot", "shot_zone_basic": "Restricted Area", "shot_zone_area": "Center(C)", "shot_distance": 0, "loc_x": -5, "loc_y": 0, "shot_made_flag": 1, "game_date": "20241203", "htm": "NYK", "vtm": "ORL", "minutes_remaining": 1, "seconds_remaining": 50}, {"player_id": 1630579, "game_id": "0022400061", "period": 2, "action_type": "Cutting Dunk Shot", "shot_zone_basic": "Restricted Area", "shot_zone_area": "Center(C)", "shot_distance": 1, "loc_x": -10, "loc_y": 0, "shot_made_flag": 1, "game_date": "20241022", "htm": "BOS", "vtm": "NYK", "minutes_remaining": 4, "seconds_remaining": 40}, {"player_id": 1630579, "game_id": "0022400061", "period": 4, "action_type": "Driving Hook Shot", "shot_zone_basic": "Restricted Area", "shot_zone_area": "Center(C)", "shot_distance": 3, "loc_x": -18, "loc_y": 33, "shot_made_flag": 0, "game_date": "20241022", "htm": "BOS", "vtm": "NYK", "minutes_remaining": 8, "seconds_remaining": 16}, {"player_id": 1630579, "game_id": "0022400061", "period": 4, "action_type": "Driving Reverse Layup Shot", "shot_zone_basic": "Restricted Area", "shot_zone_area": "Center(C)", "shot_distance": 2, "loc_x": -11, "loc_y": 20, "shot_made_flag": 1, "game_date": "20241022", "htm": "BOS", "vtm": "NYK", "minutes_remaining": 5, "seconds_remaining": 47}, {"player_id": 1630579, "game_id": "0022400081", "period": 4, "action_type": "Dunk Shot", "shot_zone_basic": "Restricted Area", "shot_zone_area": "Center(C)", "shot_distance": 1, "loc_x": 12, "loc_y": -6, "shot_made_flag": 1, "game_date": "20241025", "htm": "NYK", "vtm": "IND", "minutes_remaining": 2, "seconds_remaining": 36}, {"player_id": 1630579, "game_id": "0022400122", "period": 4, "action_type": "Alley Oop Layup shot", "shot_zone_basic": "In The Paint (Non-RA)", "shot_zone_area": "Center(C)", "shot_distance": 4, "loc_x": 27, "loc_y": 42, "shot_made_flag": 1, "game_date": "20241030", "htm": "MIA", "vtm": "NYK", "minutes_remaining": 9, "seconds_remaining": 15}, {"player_id": 1630579, "game_id": "0022400134", "period": 4, "action_type": "Cutting Dunk Shot", "shot_zone_basic": "Restricted Area", "shot_zone_area": "Center(C)", "shot_distance": 1, "loc_x": 12, "loc_y": 7, "shot_made_flag": 0, "game_date": "20241101", "htm": "DET", "vtm": "NYK", "minutes_remaining": 9, "seconds_remaining": 41}, {"player_id": 1630579, "game_id": "0022400189", "period": 1, "action_type": "Layup Shot", "shot_zone_basic": "Restricted Area", "shot_zone_area": "Center(C)", "shot_distance": 3, "loc_x": 5, "loc_y": 39, "shot_made_flag": 0, "game_date": "20241108", "htm": "NYK", "vtm": "MIL", "minutes_remaining": 5, "seconds_remaining": 9}, {"player_id": 1630579, "game_id": "0022400189", "period": 1, "action_type": "Putback Dunk Shot", "shot_zone_basic": "Restricted Area", "shot_zone_area": "Center(C)", "shot_distance": 0, "loc_x": 5, "loc_y": 8, "shot_made_flag": 1, "game_date": "20241108", "htm": "NYK", "vtm": "MIL", "minutes_remaining": 5, "seconds_remaining": 5}, {"player_id": 1630579, "game_id": "0022400203", "period": 3, "action_type": "Dunk Shot", "shot_zone_basic": "Restricted Area", "shot_zone_area": "Center(C)", "shot_distance": 0, "loc_x": 1, "loc_y": 8, "shot_made_flag": 1, "game_date": "20241110", "htm": "IND", "vtm": "NYK", "minutes_remaining": 3, "seconds_remaining": 28}, {"player_id": 1630579, "game_id": "0022400240", "period": 4, "action_type": "Alley Oop Dunk Shot", "shot_zone_basic": "Restricted Area", "shot_zone_area": "Center(C)", "shot_distance": 0, "loc_x": 7, "loc_y": 6, "shot_made_flag": 1, "game_date": "20241117", "htm": "NYK", "vtm": "BKN", "minutes_remaining": 5, "seconds_remaining": 25}, {"player_id": 1630579, "game_id": "0022400246", "period": 2, "action_type": "Cutting Dunk Shot", "shot_zone_basic": "Restricted Area", "shot_zone_area": "Center(C)", "shot_distance": 1, "loc_x": -5, "loc_y": 12, "shot_made_flag": 1, "game_date": "20241118", "htm": "NYK", "vtm": "WAS", "minutes_remaining": 6, "seconds_remaining": 9}, {"player_id": 1630579, "game_id": "0022400246", "period": 2, "action_type": "Floating Jump shot", "shot_zone_basic": "In The Paint (Non-RA)", "shot_zone_area": "Center(C)", "shot_distance": 6, "loc_x": -9, "loc_y": 67, "shot_made_flag": 1, "game_date": "20241118", "htm": "NYK", "vtm": "WAS", "minutes_remaining": 3, "seconds_remaining": 25}, {"player_id": 1630579, "game_id": "0022400246", "period": 3, "action_type": "Putback Layup Shot", "shot_zone_basic": "Restricted Area", "shot_zone_area": "Center(C)", "shot_distance": 1, "loc_x": -9, "loc_y": 9, "shot_made_flag": 0, "game_date": "20241118", "htm": "NYK", "vtm": "WAS", "minutes_remaining": 3, "seconds_remaining": 10}, {"player_id": 1630579, "game_id": "0022400246", "period": 3, "action_type": "Cutting Dunk Shot", "shot_zone_basic": "Restricted Area", "shot_zone_area": "Center(C)", "shot_distance": 1, "loc_x": 11, "loc_y": -8, "shot_made_flag": 1, "game_date": "20241118", "htm": "NYK", "vtm": "WAS", "minutes_remaining": 0, "seconds_remaining": 12}, {"player_id": 1630579, "game_id": "0022400257", "period": 1, "action_type": "Running Dunk Shot", "shot_zone_basic": "Restricted Area", "shot_zone_area": "Center(C)", "shot_distance": 3, "loc_x": 16, "loc_y": 26, "shot_made_flag": 1, "game_date": "20241120", "htm": "PHX", "vtm": "NYK", "minutes_remaining": 2, "seconds_remaining": 25}, {"player_id": 1630579, "game_id": "0022400257", "period": 3, "action_type": "Cutting Dunk Shot", "shot_zone_basic": "Restricted Area", "shot_zone_area": "Center(C)", "shot_distance": 3, "loc_x": -5, "loc_y": 33, "shot_made_flag": 1, "game_date": "20241120", "htm": "PHX", "vtm": "NYK", "minutes_remaining": 3, "seconds_remaining": 0}, {"player_id": 1630579, "game_id": "0022400264", "period": 1, "action_type": "Dunk Shot", "shot_zone_basic": "In The Paint (Non-RA)", "shot_zone_area": "Center(C)", "shot_distance": 4, "loc_x": 34, "loc_y": 24, "shot_made_flag": 0, "game_date": "20241123", "htm": "UTA", "vtm": "NYK", "minutes_remaining": 3, "seconds_remaining": 6}, {"player_id": 1630579, "game_id": "0022400264", "period": 3, "action_type": "Putback Dunk Shot", "shot_zone_basic": "Restricted Area", "shot_zone_area": "Center(C)", "shot_distance": 0, "loc_x": 0, "loc_y": 0, "shot_made_flag": 1, "game_date": "20241123", "htm": "UTA", "vtm": "NYK", "minutes_remaining": 4, "seconds_remaining": 27}, {"player_id": 1630579, "game_id": "0022400283", "period": 3, "action_type": "Cutting Layup Shot", "shot_zone_basic": "In The Paint (Non-RA)", "shot_zone_area": "Center(C)", "shot_distance": 4, "loc_x": -23, "loc_y": 44, "shot_made_flag": 0, "game_date": "20241125", "htm": "DEN", "vtm": "NYK", "minutes_remaining": 2, "seconds_remaining": 50}, {"player_id": 1630579, "game_id": "0022400308", "period": 3, "action_type": "Putback Dunk Shot", "shot_zone_basic": "Restricted Area", "shot_zone_area": "Center(C)", "shot_distance": 1, "loc_x": -9, "loc_y": 12, "shot_made_flag": 1, "game_date": "20241201", "htm": "NYK", "vtm": "NOP", "minutes_remaining": 4, "seconds_remaining": 23}, {"player_id": 1630579, "game_id": "0022400308", "period": 4, "action_type": "Alley Oop Dunk Shot", "shot_zone_basic": "Restricted Area", "shot_zone_area": "Center(C)", "shot_distance": 1, "loc_x": -9, "loc_y": -6, "shot_made_flag": 1, "game_date": "20241201", "htm": "NYK", "vtm": "NOP", "minutes_remaining": 2, "seconds_remaining": 48}, {"player_id": 1630579, "game_id": "0022400327", "period": 1, "action_type": "Reverse Layup Shot", "shot_zone_basic": "Restricted Area", "shot_zone_area": "Center(C)", "shot_distance": 0, "loc_x": 6, "loc_y": 2, "shot_made_flag": 0, "game_date": "20241205", "htm": "NYK", "vtm": "CHA", "minutes_remaining": 4, "seconds_remaining": 49}, {"player_id": 1630579, "game_id": "0022400367", "period": 1, "action_type": "Alley Oop Dunk Shot", "shot_zone_basic": "Restricted Area", "shot_zone_area": "Center(C)", "shot_distance": 0, "loc_x": 4, "loc_y": 7, "shot_made_flag": 1, "game_date": "20241219", "htm": "MIN", "vtm": "NYK", "minutes_remaining": 3, "seconds_remaining": 38}, {"player_id": 1630579, "game_id": "0022400367", "period": 3, "action_type": "Cutting Dunk Shot", "shot_zone_basic": "Restricted Area", "shot_zone_area": "Center(C)", "shot_distance": 0, "loc_x": -4, "loc_y": 9, "shot_made_flag": 1, "game_date": "20241219", "htm": "MIN", "vtm": "NYK", "minutes_remaining": 1, "seconds_remaining": 53}, {"player_id": 1630579, "game_id": "0022400367", "period": 3, "action_type": "Alley Oop Dunk Shot", "shot_zone_basic": "Restricted Area", "shot_zone_area": "Center(C)", "shot_distance": 1, "loc_x": -4, "loc_y": 13, "shot_made_flag": 0, "game_date": "20241219", "htm": "MIN", "vtm": "NYK", "minutes_remaining": 0, "seconds_remaining": 25}, {"player_id": 1630579, "game_id": "0022400367", "period": 4, "action_type": "Cutting Layup Shot", "shot_zone_basic": "Restricted Area", "shot_zone_area": "Center(C)", "shot_distance": 3, "loc_x": -7, "loc_y": 31, "shot_made_flag": 0, "game_date": "20241219", "htm": "MIN", "vtm": "NYK", "minutes_remaining": 10, "seconds_remaining": 54}, {"player_id": 1630579, "game_id": "0022400367", "period": 4, "action_type": "Turnaround Fadeaway shot", "shot_zone_basic": "In The Paint (Non-RA)", "shot_zone_area": "Left Side(L)", "shot_distance": 8, "loc_x": -59, "loc_y": 67, "shot_made_flag": 0, "game_date": "20241219", "htm": "MIN", "vtm": "NYK", "minutes_remaining": 4, "seconds_remaining": 53}, {"player_id": 1630579, "game_id": "0022400367", "period": 4, "action_type": "Cutting Dunk Shot", "shot_zone_basic": "Restricted Area", "shot_zone_area": "Center(C)", "shot_distance": 1, "loc_x": -6, "loc_y": 9, "shot_made_flag": 1, "game_date": "20241219", "htm": "MIN", "vtm": "NYK", "minutes_remaining": 3, "seconds_remaining": 31}, {"player_id": 1630579, "game_id": "0022400419", "period": 4, "action_type": "Tip Layup Shot", "shot_zone_basic": "In The Paint (Non-RA)", "shot_zone_area": "Center(C)", "shot_distance": 5, "loc_x": -40, "loc_y": 33, "shot_made_flag": 0, "game_date": "20241227", "htm": "ORL", "vtm": "NYK", "minutes_remaining": 0, "seconds_remaining": 38}, {"player_id": 1630579, "game_id": "0022400496", "period": 1, "action_type": "Reverse Layup Shot", "shot_zone_basic": "Restricted Area", "shot_zone_area": "Center(C)", "shot_distance": 1, "loc_x": 12, "loc_y": 7, "shot_made_flag": 0, "game_date": "20250106", "htm": "NYK", "vtm": "ORL", "minutes_remaining": 8, "seconds_remaining": 53}, {"player_id": 1630579, "game_id": "0022400496", "period": 1, "action_type": "Alley Oop Dunk Shot", "shot_zone_basic": "Restricted Area", "shot_zone_area": "Center(C)", "shot_distance": 1, "loc_x": 10, "loc_y": 5, "shot_made_flag": 1, "game_date": "20250106", "htm": "NYK", "vtm": "ORL", "minutes_remaining": 5, "seconds_remaining": 56}, {"player_id": 1630579, "game_id": "0022400496", "period": 2, "action_type": "Dunk Shot", "shot_zone_basic": "Restricted Area", "shot_zone_area": "Center(C)", "shot_distance": 0, "loc_x": 5, "loc_y": -1, "shot_made_flag": 0, "game_date": "20250106", "htm": "NYK", "vtm": "ORL", "minutes_remaining": 0, "seconds_remaining": 15}, {"player_id": 1630579, "game_id": "0022400496", "period": 3, "action_type": "Cutting Dunk Shot", "shot_zone_basic": "Restricted Area", "shot_zone_area": "Center(C)", "shot_distance": 0, "loc_x": 2, "loc_y": 8, "shot_made_flag": 1, "game_date": "20250106", "htm": "NYK", "vtm": "ORL", "minutes_remaining": 8, "seconds_remaining": 19}, {"player_id": 1630579, "game_id": "0022400561", "period": 1, "action_type": "Floating Jump shot", "shot_zone_basic": "In The Paint (Non-RA)", "shot_zone_area": "Center(C)", "shot_distance": 11, "loc_x": 5, "loc_y": 116, "shot_made_flag": 0, "game_date": "20250115", "htm": "PHI", "vtm": "NYK", "minutes_remaining": 8, "seconds_remaining": 23}, {"player_id": 1630579, "game_id": "0022400561", "period": 2, "action_type": "Putback Layup Shot", "shot_zone_basic": "Restricted Area", "shot_zone_area": "Center(C)", "shot_distance": 2, "loc_x": -9, "loc_y": 20, "shot_made_flag": 1, "game_date": "20250115", "htm": "PHI", "vtm": "NYK", "minutes_remaining": 6, "seconds_remaining": 53}, {"player_id": 1630579, "game_id": "0022400561", "period": 3, "action_type": "Cutting Dunk Shot", "shot_zone_basic": "Restricted Area", "shot_zone_area": "Center(C)", "shot_distance": 1, "loc_x": 6, "loc_y": 8, "shot_made_flag": 1, "game_date": "20250115", "htm": "PHI", "vtm": "NYK", "minutes_remaining": 10, "seconds_remaining": 56}, {"player_id": 1630579, "game_id": "0022400561", "period": 3, "action_type": "Cutting Layup Shot", "shot_zone_basic": "Restricted Area", "shot_zone_area": "Center(C)", "shot_distance": 2, "loc_x": -2, "loc_y": 26, "shot_made_flag": 0, "game_date": "20250115", "htm": "PHI", "vtm": "NYK", "minutes_remaining": 3, "seconds_remaining": 40}, {"player_id": 1630579, "game_id": "0022400561", "period": 3, "action_type": "Putback Dunk Shot", "shot_zone_basic": "Restricted Area", "shot_zone_area": "Center(C)", "shot_distance": 0, "loc_x": 0, "loc_y": 0, "shot_made_flag": 1, "game_date": "20250115", "htm": "PHI", "vtm": "NYK", "minutes_remaining": 2, "seconds_remaining": 15}, {"player_id": 1630579, "game_id": "0022400578", "period": 1, "action_type": "Hook Shot", "shot_zone_basic": "Restricted Area", "shot_zone_area": "Center(C)", "shot_distance": 3, "loc_x": -7, "loc_y": 38, "shot_made_flag": 0, "game_date": "20250117", "htm": "NYK", "vtm": "MIN", "minutes_remaining": 6, "seconds_remaining": 25}, {"player_id": 1630579, "game_id": "0022400578", "period": 2, "action_type": "Turnaround Hook Shot", "shot_zone_basic": "Restricted Area", "shot_zone_area": "Center(C)", "shot_distance": 3, "loc_x": -1, "loc_y": 38, "shot_made_flag": 0, "game_date": "20250117", "htm": "NYK", "vtm": "MIN", "minutes_remaining": 11, "seconds_remaining": 9}, {"player_id": 1630579, "game_id": "0022400653", "period": 4, "action_type": "Tip Layup Shot", "shot_zone_basic": "Restricted Area", "shot_zone_area": "Center(C)", "shot_distance": 1, "loc_x": -16, "loc_y": 7, "shot_made_flag": 1, "game_date": "20250127", "htm": "NYK", "vtm": "MEM", "minutes_remaining": 1, "seconds_remaining": 28}, {"player_id": 1630579, "game_id": "0022400817", "period": 3, "action_type": "Floating Jump shot", "shot_zone_basic": "In The Paint (Non-RA)", "shot_zone_area": "Center(C)", "shot_distance": 10, "loc_x": -27, "loc_y": 102, "shot_made_flag": 0, "game_date": "20250223", "htm": "MIL", "vtm": "MIA", "minutes_remaining": 0, "seconds_remaining": 1}, {"player_id": 1630579, "game_id": "0022400817", "period": 4, "action_type": "Alley Oop Dunk Shot", "shot_zone_basic": "Restricted Area", "shot_zone_area": "Center(C)", "shot_distance": 0, "loc_x": -2, "loc_y": 8, "shot_made_flag": 1, "game_date": "20250223", "htm": "MIL", "vtm": "MIA", "minutes_remaining": 9, "seconds_remaining": 21}, {"player_id": 1630579, "game_id": "0022400846", "period": 2, "action_type": "Alley Oop Layup shot", "shot_zone_basic": "Restricted Area", "shot_zone_area": "Center(C)", "shot_distance": 1, "loc_x": -5, "loc_y": 13, "shot_made_flag": 0, "game_date": "20250227", "htm": "MIL", "vtm": "DEN", "minutes_remaining": 11, "seconds_remaining": 26}, {"player_id": 1630579, "game_id": "0022400846", "period": 2, "action_type": "Tip Layup Shot", "shot_zone_basic": "Restricted Area", "shot_zone_area": "Center(C)", "shot_distance": 0, "loc_x": 0, "loc_y": 0, "shot_made_flag": 0, "game_date": "20250227", "htm": "MIL", "vtm": "DEN", "minutes_remaining": 11, "seconds_remaining": 25}, {"player_id": 1630579, "game_id": "0022400846", "period": 4, "action_type": "Cutting Dunk Shot", "shot_zone_basic": "Restricted Area", "shot_zone_area": "Center(C)", "shot_distance": 0, "loc_x": -2, "loc_y": 1, "shot_made_flag": 1, "game_date": "20250227", "htm": "MIL", "vtm": "DEN", "minutes_remaining": 9, "seconds_remaining": 18}, {"player_id": 1630579, "game_id": "0022400846", "period": 4, "action_type": "Turnaround Hook Shot", "shot_zone_basic": "In The Paint (Non-RA)", "shot_zone_area": "Center(C)", "shot_distance": 5, "loc_x": -10, "loc_y": 49, "shot_made_flag": 0, "game_date": "20250227", "htm": "MIL", "vtm": "DEN", "minutes_remaining": 8, "seconds_remaining": 8}, {"player_id": 1630579, "game_id": "0022400865", "period": 1, "action_type": "Turnaround Hook Shot", "shot_zone_basic": "In The Paint (Non-RA)", "shot_zone_area": "Center(C)", "shot_distance": 5, "loc_x": -34, "loc_y": 46, "shot_made_flag": 1, "game_date": "20250301", "htm": "DAL", "vtm": "MIL", "minutes_remaining": 0, "seconds_remaining": 53}, {"player_id": 1630579, "game_id": "0022400865", "period": 2, "action_type": "Cutting Dunk Shot", "shot_zone_basic": "Restricted Area", "shot_zone_area": "Center(C)", "shot_distance": 2, "loc_x": 7, "loc_y": 24, "shot_made_flag": 1, "game_date": "20250301", "htm": "DAL", "vtm": "MIL", "minutes_remaining": 11, "seconds_remaining": 9}, {"player_id": 1630579, "game_id": "0022400865", "period": 4, "action_type": "Dunk Shot", "shot_zone_basic": "Restricted Area", "shot_zone_area": "Center(C)", "shot_distance": 1, "loc_x": 5, "loc_y": 16, "shot_made_flag": 1, "game_date": "20250301", "htm": "DAL", "vtm": "MIL", "minutes_remaining": 5, "seconds_remaining": 40}, {"player_id": 1630579, "game_id": "0022400884", "period": 2, "action_type": "Running Dunk Shot", "shot_zone_basic": "Restricted Area", "shot_zone_area": "Center(C)", "shot_distance": 0, "loc_x": -2, "loc_y": -2, "shot_made_flag": 1, "game_date": "20250304", "htm": "ATL", "vtm": "MIL", "minutes_remaining": 11, "seconds_remaining": 14}, {"player_id": 1630579, "game_id": "0022400884", "period": 4, "action_type": "Dunk Shot", "shot_zone_basic": "Restricted Area", "shot_zone_area": "Center(C)", "shot_distance": 1, "loc_x": -9, "loc_y": 6, "shot_made_flag": 0, "game_date": "20250304", "htm": "ATL", "vtm": "MIL", "minutes_remaining": 11, "seconds_remaining": 17}, {"player_id": 1630579, "game_id": "0022400897", "period": 2, "action_type": "Alley Oop Dunk Shot", "shot_zone_basic": "Restricted Area", "shot_zone_area": "Center(C)", "shot_distance": 3, "loc_x": 36, "loc_y": 14, "shot_made_flag": 1, "game_date": "20250305", "htm": "MIL", "vtm": "DAL", "minutes_remaining": 11, "seconds_remaining": 26}, {"player_id": 1630579, "game_id": "0022400897", "period": 4, "action_type": "Cutting Layup Shot", "shot_zone_basic": "Restricted Area", "shot_zone_area": "Center(C)", "shot_distance": 2, "loc_x": -20, "loc_y": 19, "shot_made_flag": 1, "game_date": "20250305", "htm": "MIL", "vtm": "DAL", "minutes_remaining": 10, "seconds_remaining": 37}, {"player_id": 1630579, "game_id": "0022400897", "period": 4, "action_type": "Tip Layup Shot", "shot_zone_basic": "Restricted Area", "shot_zone_area": "Center(C)", "shot_distance": 2, "loc_x": 23, "loc_y": 13, "shot_made_flag": 1, "game_date": "20250305", "htm": "MIL", "vtm": "DAL", "minutes_remaining": 10, "seconds_remaining": 4}, {"player_id": 1630579, "game_id": "0022400897", "period": 4, "action_type": "Floating Jump shot", "shot_zone_basic": "Mid-Range", "shot_zone_area": "Left Side(L)", "shot_distance": 11, "loc_x": -118, "loc_y": -8, "shot_made_flag": 1, "game_date": "20250305", "htm": "MIL", "vtm": "DAL", "minutes_remaining": 8, "seconds_remaining": 8}, {"player_id": 1630579, "game_id": "0022400897", "period": 4, "action_type": "Alley Oop Dunk Shot", "shot_zone_basic": "Restricted Area", "shot_zone_area": "Center(C)", "shot_distance": 3, "loc_x": -36, "loc_y": 3, "shot_made_flag": 1, "game_date": "20250305", "htm": "MIL", "vtm": "DAL", "minutes_remaining": 5, "seconds_remaining": 14}, {"player_id": 1630579, "game_id": "0022400917", "period": 3, "action_type": "Driving Dunk Shot", "shot_zone_basic": "Restricted Area", "shot_zone_area": "Center(C)", "shot_distance": 1, "loc_x": 2, "loc_y": 13, "shot_made_flag": 1, "game_date": "20250308", "htm": "MIL", "vtm": "ORL", "minutes_remaining": 0, "seconds_remaining": 14}, {"player_id": 1630579, "game_id": "0022400922", "period": 4, "action_type": "Tip Layup Shot", "shot_zone_basic": "Restricted Area", "shot_zone_area": "Center(C)", "shot_distance": 1, "loc_x": 4, "loc_y": 17, "shot_made_flag": 0, "game_date": "20250309", "htm": "MIL", "vtm": "CLE", "minutes_remaining": 7, "seconds_remaining": 38}, {"player_id": 1630579, "game_id": "0022400942", "period": 1, "action_type": "Alley Oop Dunk Shot", "shot_zone_basic": "Restricted Area", "shot_zone_area": "Center(C)", "shot_distance": 1, "loc_x": -7, "loc_y": -10, "shot_made_flag": 1, "game_date": "20250311", "htm": "IND", "vtm": "MIL", "minutes_remaining": 2, "seconds_remaining": 15}, {"player_id": 1630579, "game_id": "0022400942", "period": 2, "action_type": "Cutting Dunk Shot", "shot_zone_basic": "Restricted Area", "shot_zone_area": "Center(C)", "shot_distance": 2, "loc_x": -6, "loc_y": 26, "shot_made_flag": 1, "game_date": "20250311", "htm": "IND", "vtm": "MIL", "minutes_remaining": 8, "seconds_remaining": 37}, {"player_id": 1630579, "game_id": "0022400942", "period": 4, "action_type": "Cutting Dunk Shot", "shot_zone_basic": "Restricted Area", "shot_zone_area": "Center(C)", "shot_distance": 0, "loc_x": 0, "loc_y": 4, "shot_made_flag": 1, "game_date": "20250311", "htm": "IND", "vtm": "MIL", "minutes_remaining": 10, "seconds_remaining": 22}, {"player_id": 1630579, "game_id": "0022400955", "period": 1, "action_type": "Alley Oop Dunk Shot", "shot_zone_basic": "Restricted Area", "shot_zone_area": "Center(C)", "shot_distance": 1, "loc_x": -2, "loc_y": 16, "shot_made_flag": 1, "game_date": "20250313", "htm": "MIL", "vtm": "LAL", "minutes_remaining": 0, "seconds_remaining": 16}, {"player_id": 1630579, "game_id": "0022400955", "period": 2, "action_type": "Alley Oop Dunk Shot", "shot_zone_basic": "Restricted Area", "shot_zone_area": "Center(C)", "shot_distance": 0, "loc_x": -6, "loc_y": 6, "shot_made_flag": 1, "game_date": "20250313", "htm": "MIL", "vtm": "LAL", "minutes_remaining": 9, "seconds_remaining": 35}, {"player_id": 1630579, "game_id": "0022400982", "period": 2, "action_type": "Tip Layup Shot", "shot_zone_basic": "Restricted Area", "shot_zone_area": "Center(C)", "shot_distance": 0, "loc_x": 0, "loc_y": 0, "shot_made_flag": 0, "game_date": "20250316", "htm": "MIL", "vtm": "OKC", "minutes_remaining": 7, "seconds_remaining": 47}, {"player_id": 1630579, "game_id": "0022400982", "period": 3, "action_type": "Cutting Layup Shot", "shot_zone_basic": "Restricted Area", "shot_zone_area": "Center(C)", "shot_distance": 2, "loc_x": 15, "loc_y": 21, "shot_made_flag": 0, "game_date": "20250316", "htm": "MIL", "vtm": "OKC", "minutes_remaining": 2, "seconds_remaining": 8}]