[{"player_id": 1631210, "game_id": "0022300736", "period": 2, "action_type": "Jump Shot", "shot_zone_basic": "Right Corner 3", "shot_zone_area": "Right Side(R)", "shot_distance": 23, "loc_x": 233, "loc_y": -11, "shot_made_flag": 0, "game_date": "20240208", "htm": "NYK", "vtm": "DAL", "minutes_remaining": 2, "seconds_remaining": 41}, {"player_id": 1631210, "game_id": "0022300736", "period": 4, "action_type": "Tip Dunk Shot", "shot_zone_basic": "Restricted Area", "shot_zone_area": "Center(C)", "shot_distance": 0, "loc_x": 0, "loc_y": 0, "shot_made_flag": 1, "game_date": "20240208", "htm": "NYK", "vtm": "DAL", "minutes_remaining": 5, "seconds_remaining": 9}, {"player_id": 1631210, "game_id": "0022300778", "period": 4, "action_type": "Jump Shot", "shot_zone_basic": "Above the Break 3", "shot_zone_area": "Left Side Center(LC)", "shot_distance": 25, "loc_x": -146, "loc_y": 203, "shot_made_flag": 0, "game_date": "20240214", "htm": "ORL", "vtm": "NYK", "minutes_remaining": 11, "seconds_remaining": 41}, {"player_id": 1631210, "game_id": "0022300778", "period": 4, "action_type": "Cutting Dunk Shot", "shot_zone_basic": "Restricted Area", "shot_zone_area": "Center(C)", "shot_distance": 3, "loc_x": -10, "loc_y": 36, "shot_made_flag": 1, "game_date": "20240214", "htm": "ORL", "vtm": "NYK", "minutes_remaining": 10, "seconds_remaining": 10}, {"player_id": 1631210, "game_id": "0022300778", "period": 4, "action_type": "Pullup Jump shot", "shot_zone_basic": "Above the Break 3", "shot_zone_area": "Right Side Center(RC)", "shot_distance": 26, "loc_x": 108, "loc_y": 237, "shot_made_flag": 0, "game_date": "20240214", "htm": "ORL", "vtm": "NYK", "minutes_remaining": 7, "seconds_remaining": 30}, {"player_id": 1631210, "game_id": "0022300778", "period": 4, "action_type": "Driving Layup Shot", "shot_zone_basic": "In The Paint (Non-RA)", "shot_zone_area": "Center(C)", "shot_distance": 6, "loc_x": 55, "loc_y": 27, "shot_made_flag": 0, "game_date": "20240214", "htm": "ORL", "vtm": "NYK", "minutes_remaining": 6, "seconds_remaining": 26}, {"player_id": 1631210, "game_id": "0022300778", "period": 4, "action_type": "Running Alley Oop Dunk Shot", "shot_zone_basic": "Restricted Area", "shot_zone_area": "Center(C)", "shot_distance": 0, "loc_x": -6, "loc_y": 6, "shot_made_flag": 1, "game_date": "20240214", "htm": "ORL", "vtm": "NYK", "minutes_remaining": 4, "seconds_remaining": 9}, {"player_id": 1631210, "game_id": "0022300778", "period": 4, "action_type": "Jump Shot", "shot_zone_basic": "Above the Break 3", "shot_zone_area": "Left Side Center(LC)", "shot_distance": 25, "loc_x": -194, "loc_y": 161, "shot_made_flag": 1, "game_date": "20240214", "htm": "ORL", "vtm": "NYK", "minutes_remaining": 3, "seconds_remaining": 7}, {"player_id": 1631210, "game_id": "0022300778", "period": 4, "action_type": "Pullup Jump shot", "shot_zone_basic": "Mid-Range", "shot_zone_area": "Left Side(L)", "shot_distance": 16, "loc_x": -164, "loc_y": 6, "shot_made_flag": 1, "game_date": "20240214", "htm": "ORL", "vtm": "NYK", "minutes_remaining": 0, "seconds_remaining": 59}]