[{"player_id": 1641879, "game_id": "0022400812", "period": 4, "action_type": "Step Back Jump shot", "shot_zone_basic": "In The Paint (Non-RA)", "shot_zone_area": "Center(C)", "shot_distance": 11, "loc_x": -33, "loc_y": 110, "shot_made_flag": 0, "game_date": "20250223", "htm": "GSW", "vtm": "DAL", "minutes_remaining": 5, "seconds_remaining": 51}, {"player_id": 1641879, "game_id": "0022400812", "period": 4, "action_type": "Pullup Jump shot", "shot_zone_basic": "Mid-Range", "shot_zone_area": "Right Side Center(RC)", "shot_distance": 17, "loc_x": 130, "loc_y": 121, "shot_made_flag": 1, "game_date": "20250223", "htm": "GSW", "vtm": "DAL", "minutes_remaining": 1, "seconds_remaining": 5}, {"player_id": 1641879, "game_id": "0022400812", "period": 4, "action_type": "Driving Floating Jump Shot", "shot_zone_basic": "In The Paint (Non-RA)", "shot_zone_area": "Center(C)", "shot_distance": 12, "loc_x": -27, "loc_y": 126, "shot_made_flag": 0, "game_date": "20250223", "htm": "GSW", "vtm": "DAL", "minutes_remaining": 0, "seconds_remaining": 41}]