{"last5": {"gp": 5.0, "w": 1.0, "l": 4.0, "min": 23.7, "fgm": 2.8, "fga": 7.2, "fg_pct": 0.389, "fg3m": 0.4, "fg3a": 1.2, "fg3_pct": 0.333, "ftm": 4.2, "fta": 5.6, "ft_pct": 0.75, "oreb": 1.8, "dreb": 2.2, "reb": 4.0, "ast": 2.4, "tov": 1.6, "stl": 1.0, "blk": 0.4, "pf": 3.2, "pts": 10.2, "plus_minus": -8.6}, "last10": {"gp": 10.0, "w": 3.0, "l": 7.0, "min": 25.0, "fgm": 3.6, "fga": 6.9, "fg_pct": 0.522, "fg3m": 0.7, "fg3a": 1.6, "fg3_pct": 0.438, "ftm": 2.8, "fta": 3.7, "ft_pct": 0.757, "oreb": 1.7, "dreb": 2.9, "reb": 4.6, "ast": 3.4, "tov": 2.3, "stl": 1.1, "blk": 0.6, "pf": 3.3, "pts": 10.7, "plus_minus": -7.5}, "last15": {"gp": 15.0, "w": 3.0, "l": 12.0, "min": 25.6, "fgm": 3.5, "fga": 7.1, "fg_pct": 0.495, "fg3m": 0.6, "fg3a": 1.5, "fg3_pct": 0.391, "ftm": 2.5, "fta": 3.3, "ft_pct": 0.755, "oreb": 1.6, "dreb": 3.1, "reb": 4.7, "ast": 3.7, "tov": 2.1, "stl": 1.0, "blk": 0.7, "pf": 3.4, "pts": 10.1, "plus_minus": -4.0}, "last20": {"gp": 20.0, "w": 6.0, "l": 14.0, "min": 25.4, "fgm": 3.8, "fga": 7.5, "fg_pct": 0.5, "fg3m": 0.7, "fg3a": 1.8, "fg3_pct": 0.389, "ftm": 2.5, "fta": 3.3, "ft_pct": 0.754, "oreb": 1.9, "dreb": 4.0, "reb": 5.9, "ast": 3.6, "tov": 2.1, "stl": 0.9, "blk": 0.6, "pf": 3.2, "pts": 10.7, "plus_minus": -0.9}}